Workbook

Sheet USA
A1: Year | B1: Unemployment rate | C1: Nominal GDP | D1: Real GDP | E1: CPI ( base = 1982-84) | F1: Population (thousands) | H1: GDP Deflator | I1: GDP Deflator Index (2000=100) | J1: Real GDP per Capita (USD/person) | K1: Real GDP per Capita Index (2000=100) | L1: Real GDP Growth (%) | M1: Potential GDP (Linear Trend) | N1: Output Gap (%) | O1: CPI Inflation Rate (%) | P1: GDP Deflator Inflation Rate (%) | Q1: Change in Unemployment Rate (pp) | R1: Average Unemployment Rate (%) | S1: Unemployment Gap (pp)
A2: 36526 | B2: 4 | C2: 10250.952 | D2: 14096.033 | E2: 172.192 | F2: 282398 | H2: =C2/D2*100 -> 72.722247 | I2: =H2/$H$2*100 -> 100 | J2: =(D2*1000000000)/(F2*1000) -> 49915.485 | K2: =J2/$J$2*100 -> 100 | M2: {=TREND($D$2:$D$26,$A$2:$A$26,A2)} -> 13714.535 | N2: =(D2-M2)/M2*100 -> 2.7817049 | R2: =AVERAGE($B$2:$B$26) -> 5.704 | S2: =B2-R2 -> -1.704
A3: 36892 | B3: 4.7 | C3: 10581.929 | D3: 14230.726 | E3: 177.042 | F3: 285225 | H3: =C3/D3*100 -> 74.359727 | I3: =H3/$H$2*100 -> 102.25169 | J3: =(D3*1000000000)/(F3*1000) -> 49892.983 | K3: =J3/$J$2*100 -> 99.95492 | L3: =(D3-D2)/D2*100 -> 0.95553834 | M3: {=TREND($D$2:$D$26,$A$2:$A$26,A3)} -> 14076.494 | N3: =(D3-M3)/M3*100 -> 1.0956702 | O3: =(E3-E2)/E2*100 -> 2.8166233 | P3: =(H3-H2)/H2*100 -> 2.2516899 | Q3: =B3-B2 -> 0.7 | R3: =AVERAGE($B$2:$B$26) -> 5.704 | S3: =B3-R3 -> -1.004
A4: 37257 | B4: 5.8 | C4: 10929.108 | D4: 14472.712 | E4: 179.867 | F4: 287955 | H4: =C4/D4*100 -> 75.515273 | I4: =H4/$H$2*100 -> 103.84068 | J4: =(D4*1000000000)/(F4*1000) -> 50260.325 | K4: =J4/$J$2*100 -> 100.69085 | L4: =(D4-D3)/D3*100 -> 1.7004473 | M4: {=TREND($D$2:$D$26,$A$2:$A$26,A4)} -> 14437.464 | N4: =(D4-M4)/M4*100 -> 0.24414229 | O4: =(E4-E3)/E3*100 -> 1.5956666 | P4: =(H4-H3)/H3*100 -> 1.5539947 | Q4: =B4-B3 -> 1.1 | R4: =AVERAGE($B$2:$B$26) -> 5.704 | S4: =B4-R4 -> 0.096
A5: 37622 | B5: 6 | C5: 11456.45 | D5: 14877.313 | E5: 184 | F5: 290626 | H5: =C5/D5*100 -> 77.006177 | I5: =H5/$H$2*100 -> 105.89081 | J5: =(D5*1000000000)/(F5*1000) -> 51190.578 | K5: =J5/$J$2*100 -> 102.55451 | L5: =(D5-D4)/D4*100 -> 2.7956129 | M5: {=TREND($D$2:$D$26,$A$2:$A$26,A5)} -> 14798.434 | N5: =(D5-M5)/M5*100 -> 0.53302239 | O5: =(E5-E4)/E4*100 -> 2.2978089 | P5: =(H5-H4)/H4*100 -> 1.9743079 | Q5: =B5-B4 -> 0.2 | R5: =AVERAGE($B$2:$B$26) -> 5.704 | S5: =B5-R5 -> 0.296
A6: 37987 | B6: 5.5 | C6: 12217.196 | D6: 15449.757 | E6: 188.908 | F6: 293262 | H6: =C6/D6*100 -> 79.076946 | I6: =H6/$H$2*100 -> 108.73831 | J6: =(D6*1000000000)/(F6*1000) -> 52682.438 | K6: =J6/$J$2*100 -> 105.54328 | L6: =(D6-D5)/D5*100 -> 3.8477647 | M6: {=TREND($D$2:$D$26,$A$2:$A$26,A6)} -> 15159.404 | N6: =(D6-M6)/M6*100 -> 1.9153324 | O6: =(E6-E5)/E5*100 -> 2.6673913 | P6: =(H6-H5)/H5*100 -> 2.6890945 | Q6: =B6-B5 -> -0.5 | R6: =AVERAGE($B$2:$B$26) -> 5.704 | S6: =B6-R6 -> -0.204
A7: 38353 | B7: 5.1 | C7: 13039.197 | D7: 15987.958 | E7: 195.267 | F7: 295993 | H7: =C7/D7*100 -> 81.556363 | I7: =H7/$H$2*100 -> 112.14775 | J7: =(D7*1000000000)/(F7*1000) -> 54014.649 | K7: =J7/$J$2*100 -> 108.21221 | L7: =(D7-D6)/D6*100 -> 3.4835564 | M7: {=TREND($D$2:$D$26,$A$2:$A$26,A7)} -> 15521.363 | N7: =(D7-M7)/M7*100 -> 3.0061473 | O7: =(E7-E6)/E6*100 -> 3.3661888 | P7: =(H7-H6)/H6*100 -> 3.1354481 | Q7: =B7-B6 -> -0.4 | R7: =AVERAGE($B$2:$B$26) -> 5.704 | S7: =B7-R7 -> -0.604
A8: 38718 | B8: 4.6 | C8: 13815.583 | D8: 16433.148 | E8: 201.558 | F8: 298818 | H8: =C8/D8*100 -> 84.071433 | I8: =H8/$H$2*100 -> 115.60621 | J8: =(D8*1000000000)/(F8*1000) -> 54993.836 | K8: =J8/$J$2*100 -> 110.1739 | L8: =(D8-D7)/D7*100 -> 2.7845332 | M8: {=TREND($D$2:$D$26,$A$2:$A$26,A8)} -> 15882.333 | N8: =(D8-M8)/M8*100 -> 3.4680991 | O8: =(E8-E7)/E7*100 -> 3.2217425 | P8: =(H8-H7)/H7*100 -> 3.0838432 | Q8: =B8-B7 -> -0.5 | R8: =AVERAGE($B$2:$B$26) -> 5.704 | S8: =B8-R8 -> -1.104
A9: 39083 | B9: 4.6 | C9: 14474.227 | D9: 16762.446 | E9: 207.344 | F9: 301696 | H9: =C9/D9*100 -> 86.349134 | I9: =H9/$H$2*100 -> 118.73826 | J9: =(D9*1000000000)/(F9*1000) -> 55560.717 | K9: =J9/$J$2*100 -> 111.30958 | L9: =(D9-D8)/D8*100 -> 2.0038644 | M9: {=TREND($D$2:$D$26,$A$2:$A$26,A9)} -> 16243.303 | N9: =(D9-M9)/M9*100 -> 3.1960436 | O9: =(E9-E8)/E8*100 -> 2.8706377 | P9: =(H9-H8)/H8*100 -> 2.7092453 | Q9: =B9-B8 -> 0 | R9: =AVERAGE($B$2:$B$26) -> 5.704 | S9: =B9-R9 -> -1.104
A10: 39448 | B10: 5.8 | C10: 14769.862 | D10: 16781.485 | E10: 215.254 | F10: 304543 | H10: =C10/D10*100 -> 88.012843 | I10: =H10/$H$2*100 -> 121.02602 | J10: =(D10*1000000000)/(F10*1000) -> 55103.828 | K10: =J10/$J$2*100 -> 110.39426 | L10: =(D10-D9)/D9*100 -> 0.11358128 | M10: {=TREND($D$2:$D$26,$A$2:$A$26,A10)} -> 16604.273 | N10: =(D10-M10)/M10*100 -> 1.0672678 | O10: =(E10-E9)/E9*100 -> 3.8149163 | P10: =(H10-H9)/H9*100 -> 1.9267228 | Q10: =B10-B9 -> 1.2 | R10: =AVERAGE($B$2:$B$26) -> 5.704 | S10: =B10-R10 -> 0.096
A11: 39814 | B11: 9.3 | C11: 14478.067 | D11: 16349.111 | E11: 214.565 | F11: 307240 | H11: =C11/D11*100 -> 88.555684 | I11: =H11/$H$2*100 -> 121.77248 | J11: =(D11*1000000000)/(F11*1000) -> 53212.834 | K11: =J11/$J$2*100 -> 106.60586 | L11: =(D11-D10)/D10*100 -> -2.5764943 | M11: {=TREND($D$2:$D$26,$A$2:$A$26,A11)} -> 16966.232 | N11: =(D11-M11)/M11*100 -> -3.6373479 | O11: =(E11-E10)/E10*100 -> -0.32008697 | P11: =(H11-H10)/H10*100 -> 0.61677456 | Q11: =B11-B10 -> 3.5 | R11: =AVERAGE($B$2:$B$26) -> 5.704 | S11: =B11-R11 -> 3.596
A12: 40179 | B12: 9.6 | C12: 15048.971 | D12: 16789.751 | E12: 218.076 | F12: 309839 | H12: =C12/D12*100 -> 89.631889 | I12: =H12/$H$2*100 -> 123.25236 | J12: =(D12*1000000000)/(F12*1000) -> 54188.63 | K12: =J12/$J$2*100 -> 108.56076 | L12: =(D12-D11)/D11*100 -> 2.6951924 | M12: {=TREND($D$2:$D$26,$A$2:$A$26,A12)} -> 17327.202 | N12: =(D12-M12)/M12*100 -> -3.1017753 | O12: =(E12-E11)/E11*100 -> 1.636334 | P12: =(H12-H11)/H11*100 -> 1.2152868 | Q12: =B12-B11 -> 0.3 | R12: =AVERAGE($B$2:$B$26) -> 5.704 | S12: =B12-R12 -> 3.896
A13: 40544 | B13: 8.9 | C13: 15599.732 | D13: 17052.411 | E13: 224.923 | F13: 312295 | H13: =C13/D13*100 -> 91.481093 | I13: =H13/$H$2*100 -> 125.7952 | J13: =(D13*1000000000)/(F13*1000) -> 54603.535 | K13: =J13/$J$2*100 -> 109.39198 | L13: =(D13-D12)/D12*100 -> 1.5644068 | M13: {=TREND($D$2:$D$26,$A$2:$A$26,A13)} -> 17688.172 | N13: =(D13-M13)/M13*100 -> -3.5942712 | O13: =(E13-E12)/E12*100 -> 3.1397311 | P13: =(H13-H12)/H12*100 -> 2.0631096 | Q13: =B13-B12 -> -0.7 | R13: =AVERAGE($B$2:$B$26) -> 5.704 | S13: =B13-R13 -> 3.196
A14: 40909 | B14: 8.1 | C14: 16253.97 | D14: 17442.759 | E14: 229.586 | F14: 314725 | H14: =C14/D14*100 -> 93.184628 | I14: =H14/$H$2*100 -> 128.13772 | J14: =(D14*1000000000)/(F14*1000) -> 55422.223 | K14: =J14/$J$2*100 -> 111.03212 | L14: =(D14-D13)/D13*100 -> 2.2891074 | M14: {=TREND($D$2:$D$26,$A$2:$A$26,A14)} -> 18049.142 | N14: =(D14-M14)/M14*100 -> -3.3596215 | O14: =(E14-E13)/E13*100 -> 2.0731539 | P14: =(H14-H13)/H13*100 -> 1.8621709 | Q14: =B14-B13 -> -0.8 | R14: =AVERAGE($B$2:$B$26) -> 5.704 | S14: =B14-R14 -> 2.396
... A26: 45292 | B26: 4 | C26: 29298.013 | D26: 23358.435 | E26: 313.698 | F26: 340095 | H26: =C26/D26*100 -> 125.42798 | I26: =H26/$H$2*100 -> 172.47539 | J26: =(D26*1000000000)/(F26*1000) -> 68682.089 | K26: =J26/$J$2*100 -> 137.59676 | L26: =(D26-D25)/D25*100 -> 2.7931872 | M26: {=TREND($D$2:$D$26,$A$2:$A$26,A26)} -> 22383.749 | N26: =(D26-M26)/M26*100 -> 4.3544377 | O26: =(E26-E25)/E25*100 -> 2.952055 | P26: =(H26-H25)/H25*100 -> 2.4823693 | Q26: =B26-B25 -> 0.4 | R26: =AVERAGE($B$2:$B$26) -> 5.704 | S26: =B26-R26 -> -1.704
A27: Data Sources | B27: FRED `UNRATE` | C27: FRED `GDP` | D27: FRED `GDPC1` | E27: FRED `CPIAUCSL` | F27: FRED `POPTHM` | H27: Excel formula | I27: Excel formula | J27: Excel formula | K27: Excel formula | L27: Excel formula | M27: Excel formula | N27: Excel formula | O27: Excel formula | P27: Excel formula | Q27: Excel formula | R27: Excel formula | S27: Excel formula
H28: Nominal GDP / Real GDP × 100 | I28: GDP Deflator / GDP Deflator in 2000 × 100 | J28: (Real GDP × 1,000,000,000) / (Population × 1,000) | K28: Real GDP per Capita / 2000 value × 100 | L28: (Real GDP_t − Real GDP_t−1) / Real GDP_t−1 × 100 | M28: TREND(Real GDP 2000–2024, time 2000–2024) | N28: (Actual Real GDP − Potential GDP) / Potential GDP × 100 | O28: (CPI_t − CPI_t−1) / CPI_t−1 × 100 | P28: (Deflator_t − Deflator_t−1) / Deflator_t−1 × 100 | Q28: Unemployment_t − Unemployment_t−1 | R28: AVERAGE(Unemployment, 2000–2024) | S28: Actual unemployment − full-sample average
A29: sample period | B29: 2000–2024 | C29: 2000–2024 | D29: 2000–2024 | E29: 2000–2024 | F29: 2000–2024 | G29: valid | H29: 2000–2024 | I29: 2000–2024 | J29: 2000–2024 | K29: 2000–2024 | L29: 2001–2024 | M29: 2000–2024 | N29: 2000–2024 | O29: 2001–2024 | P29: 2001–2024 | Q29: 2001–2024 | R29: 2000–2024 | S29: 2000–2024
A30: type | B30: Monthly unemployment rate (%) | C30: Quarterly GDP, SAAR | D30: Quarterly real GDP, SAAR | E30: Monthly CPI index (1982–1984 = 100) | F30: Monthly population (thousands) | G30: inputs | H30: C, D | I30: H | J30: D, F | K30: J | L30: D | M30: A, D | N30: D, M | O30: E | P30: H | Q30: B | R30: B | S30: B, R
A31: Data processing | B31: Converted to annual using the annual average. | C31: Quarterly SAAR observations were averaged to annual values. | D31: Quarterly SAAR observations were averaged to annual values. | E31: Converted to annual using the annual average. | F31: Converted to annual using the annual average. | G31: purpose | H31: Implicit price index for domestic output. | I31: Re-bases each country's deflator so 2000 = 100 for comparison. | J31: Converts GDP to dollars and population to persons before division. | K31: Measures cumulative real-GDP-per-capita growth since 2000. | L31: Year-over-year real output growth. | M31: Full-sample linear trend used as the homework proxy for potential GDP. | N31: Measures actual output relative to the linear-trend proxy. | O31: Annual CPI inflation. | P31: Annual inflation implied by the GDP deflator. | Q31: Percentage-point change in unemployment; used in Okun scatter plot. | R31: Simple benchmark for the 'normal' unemployment rate in Q9. | S31: Positive values mean unemployment is above its 2000–2024 average.

Sheet Germany
A1: Year | B1: Unemployment rate | C1: Nominal GDP | D1: Real GDP | E1: CPI (base = 2015) | F1: Population(person) | H1: GDP Deflator | I1: GDP Deflator Index (2000=100) | J1: Real GDP per Capita (EUR/person) | K1: Real GDP per Capita Index (2000=100) | L1: Real GDP Growth (%) | M1: Potential GDP (Linear Trend) | N1: Output Gap (%) | O1: CPI Inflation Rate (%) | P1: GDP Deflator Inflation Rate (%) | Q1: Change in Unemployment Rate (pp) | R1: Average Unemployment Rate (%) | S1: Unemployment Gap (pp)
A2: 36526 | B2: 8 | C2: 2129688 | D2: 2395647.2 | E2: 79.943527 | F2: 82211508 | H2: =C2/D2*100 -> 88.898232 | I2: =H2/$H$2*100 -> 100 | J2: =(D2*1000000)/F2 -> 29140.047 | K2: =J2/$J$2*100 -> 100 | M2: {=TREND($D$2:$D$26,$A$2:$A$26,A2)} -> 2346612.9 | N2: =(D2-M2)/M2*100 -> 2.0895782 | R2: =AVERAGE($B$2:$B$26) -> 6.024 | S2: =B2-R2 -> 1.976
A3: 36892 | B3: 7.8 | C3: 2198354 | D3: 2437867.5 | E3: 81.529488 | F3: 82349925 | H3: =C3/D3*100 -> 90.175286 | I3: =H3/$H$2*100 -> 101.43654 | J3: =(D3*1000000)/F3 -> 29603.761 | K3: =J3/$J$2*100 -> 101.59133 | L3: =(D3-D2)/D2*100 -> 1.7623755 | M3: {=TREND($D$2:$D$26,$A$2:$A$26,A3)} -> 2380212.3 | N3: =(D3-M3)/M3*100 -> 2.4222733 | O3: =(E3-E2)/E2*100 -> 1.9838525 | P3: =(H3-H2)/H2*100 -> 1.4365355 | Q3: =B3-B2 -> -0.2 | R3: =AVERAGE($B$2:$B$26) -> 6.024 | S3: =B3-R3 -> 1.776
A4: 37257 | B4: 8.6 | C4: 2227073 | D4: 2433299.2 | E4: 82.687866 | F4: 82488495 | H4: =C4/D4*100 -> 91.524832 | I4: =H4/$H$2*100 -> 102.95461 | J4: =(D4*1000000)/F4 -> 29498.649 | K4: =J4/$J$2*100 -> 101.23062 | L4: =(D4-D3)/D3*100 -> -0.18738918 | M4: {=TREND($D$2:$D$26,$A$2:$A$26,A4)} -> 2413719.8 | N4: =(D4-M4)/M4*100 -> 0.81117041 | O4: =(E4-E3)/E3*100 -> 1.420808 | P4: =(H4-H3)/H3*100 -> 1.4965801 | Q4: =B4-B3 -> 0.8 | R4: =AVERAGE($B$2:$B$26) -> 6.024 | S4: =B4-R4 -> 2.576
A5: 37622 | B5: 9.7 | C5: 2244141 | D5: 2419815.1 | E5: 83.543044 | F5: 82534176 | H5: =C5/D5*100 -> 92.740185 | I5: =H5/$H$2*100 -> 104.32174 | J5: =(D5*1000000)/F5 -> 29318.947 | K5: =J5/$J$2*100 -> 100.61393 | L5: =(D5-D4)/D4*100 -> -0.55414887 | M5: {=TREND($D$2:$D$26,$A$2:$A$26,A5)} -> 2447227.4 | N5: =(D5-M5)/M5*100 -> -1.1201363 | O5: =(E5-E4)/E4*100 -> 1.0342247 | P5: =(H5-H4)/H4*100 -> 1.3278945 | Q5: =B5-B4 -> 1.1 | R5: =AVERAGE($B$2:$B$26) -> 6.024 | S5: =B5-R5 -> 3.676
A6: 37987 | B6: 10.3 | C6: 2285493 | D6: 2436467.6 | E6: 84.934648 | F6: 82516260 | H6: =C6/D6*100 -> 93.803546 | I6: =H6/$H$2*100 -> 105.5179 | J6: =(D6*1000000)/F6 -> 29527.121 | K6: =J6/$J$2*100 -> 101.32832 | L6: =(D6-D5)/D5*100 -> 0.68817241 | M6: {=TREND($D$2:$D$26,$A$2:$A$26,A6)} -> 2480734.9 | N6: =(D6-M6)/M6*100 -> -1.7844449 | O6: =(E6-E5)/E5*100 -> 1.6657331 | P6: =(H6-H5)/H5*100 -> 1.146602 | Q6: =B6-B5 -> 0.6 | R6: =AVERAGE($B$2:$B$26) -> 6.024 | S6: =B6-R6 -> 4.276
A7: 38353 | B7: 11 | C7: 2322042 | D7: 2462256.5 | E7: 86.248512 | F7: 82469422 | H7: =C7/D7*100 -> 94.305447 | I7: =H7/$H$2*100 -> 106.08248 | J7: =(D7*1000000)/F7 -> 29856.599 | K7: =J7/$J$2*100 -> 102.459 | L7: =(D7-D6)/D6*100 -> 1.0584545 | M7: {=TREND($D$2:$D$26,$A$2:$A$26,A7)} -> 2514334.3 | N7: =(D7-M7)/M7*100 -> -2.0712366 | O7: =(E7-E6)/E6*100 -> 1.5469109 | P7: =(H7-H6)/H6*100 -> 0.53505579 | Q7: =B7-B6 -> 0.7 | R7: =AVERAGE($B$2:$B$26) -> 6.024 | S7: =B7-R7 -> 4.976
A8: 38718 | B8: 10.1 | C8: 2426834 | D8: 2561949.3 | E8: 87.609024 | F8: 82376451 | H8: =C8/D8*100 -> 94.726074 | I8: =H8/$H$2*100 -> 106.55563 | J8: =(D8*1000000)/F8 -> 31100.506 | K8: =J8/$J$2*100 -> 106.72771 | L8: =(D8-D7)/D7*100 -> 4.0488389 | M8: {=TREND($D$2:$D$26,$A$2:$A$26,A8)} -> 2547841.9 | N8: =(D8-M8)/M8*100 -> 0.55370088 | O8: =(E8-E7)/E7*100 -> 1.577433 | P8: =(H8-H7)/H7*100 -> 0.44602656 | Q8: =B8-B7 -> -0.9 | R8: =AVERAGE($B$2:$B$26) -> 6.024 | S8: =B8-R8 -> 4.076
A9: 39083 | B9: 8.6 | C9: 2545653 | D9: 2638874.1 | E9: 89.622573 | F9: 82266372 | H9: =C9/D9*100 -> 96.467391 | I9: =H9/$H$2*100 -> 108.51441 | J9: =(D9*1000000)/F9 -> 32077.191 | K9: =J9/$J$2*100 -> 110.07941 | L9: =(D9-D8)/D8*100 -> 3.0025887 | M9: {=TREND($D$2:$D$26,$A$2:$A$26,A9)} -> 2581349.4 | N9: =(D9-M9)/M9*100 -> 2.2284724 | O9: =(E9-E8)/E8*100 -> 2.2983353 | P9: =(H9-H8)/H8*100 -> 1.8382655 | Q9: =B9-B8 -> -1.5 | R9: =AVERAGE($B$2:$B$26) -> 6.024 | S9: =B9-R9 -> 2.576
A10: 39448 | B10: 7.4 | C10: 2585733 | D10: 2654937 | E10: 91.978202 | F10: 82110097 | H10: =C10/D10*100 -> 97.393384 | I10: =H10/$H$2*100 -> 109.55604 | J10: =(D10*1000000)/F10 -> 32333.868 | K10: =J10/$J$2*100 -> 110.96025 | L10: =(D10-D9)/D9*100 -> 0.60870278 | M10: {=TREND($D$2:$D$26,$A$2:$A$26,A10)} -> 2614857 | N10: =(D10-M10)/M10*100 -> 1.5327796 | O10: =(E10-E9)/E9*100 -> 2.6283882 | P10: =(H10-H9)/H9*100 -> 0.95990294 | Q10: =B10-B9 -> -1.2 | R10: =AVERAGE($B$2:$B$26) -> 6.024 | S10: =B10-R10 -> 1.376
A11: 39814 | B11: 7.4 | C11: 2491785 | D11: 2509045.1 | E11: 92.265852 | F11: 81902307 | H11: =C11/D11*100 -> 99.312085 | I11: =H11/$H$2*100 -> 111.71435 | J11: =(D11*1000000)/F11 -> 30634.608 | K11: =J11/$J$2*100 -> 105.12889 | L11: =(D11-D10)/D10*100 -> -5.4951172 | M11: {=TREND($D$2:$D$26,$A$2:$A$26,A11)} -> 2648456.4 | N11: =(D11-M11)/M11*100 -> -5.2638689 | O11: =(E11-E10)/E10*100 -> 0.31273714 | P11: =(H11-H10)/H10*100 -> 1.9700521 | Q11: =B11-B10 -> 0 | R11: =AVERAGE($B$2:$B$26) -> 6.024 | S11: =B11-R11 -> 1.376
A12: 40179 | B12: 6.6 | C12: 2609401 | D12: 2609401 | E12: 93.284289 | F12: 81776930 | H12: =C12/D12*100 -> 100 | I12: =H12/$H$2*100 -> 112.48818 | J12: =(D12*1000000)/F12 -> 31908.767 | K12: =J12/$J$2*100 -> 109.50143 | L12: =(D12-D11)/D11*100 -> 3.9997647 | M12: {=TREND($D$2:$D$26,$A$2:$A$26,A12)} -> 2681963.9 | N12: =(D12-M12)/M12*100 -> -2.7055895 | O12: =(E12-E11)/E11*100 -> 1.1038067 | P12: =(H12-H11)/H11*100 -> 0.69268015 | Q12: =B12-B11 -> -0.8 | R12: =AVERAGE($B$2:$B$26) -> 6.024 | S12: =B12-R12 -> 0.576
A13: 40544 | B13: 5.5 | C13: 2743043 | D13: 2709683.2 | E13: 95.220101 | F13: 80274983 | H13: =C13/D13*100 -> 101.23113 | I13: =H13/$H$2*100 -> 113.87306 | J13: =(D13*1000000)/F13 -> 33755.014 | K13: =J13/$J$2*100 -> 115.8372 | L13: =(D13-D12)/D12*100 -> 3.8431119 | M13: {=TREND($D$2:$D$26,$A$2:$A$26,A13)} -> 2715471.5 | N13: =(D13-M13)/M13*100 -> -0.21316001 | O13: =(E13-E12)/E12*100 -> 2.0751744 | P13: =(H13-H12)/H12*100 -> 1.2311328 | Q13: =B13-B12 -> -1.1 | R13: =AVERAGE($B$2:$B$26) -> 6.024 | S13: =B13-R13 -> -0.524
A14: 40909 | B14: 5.1 | C14: 2802015 | D14: 2728840.6 | E14: 97.132587 | F14: 80425823 | H14: =C14/D14*100 -> 102.68152 | I14: =H14/$H$2*100 -> 115.50457 | J14: =(D14*1000000)/F14 -> 33929.906 | K14: =J14/$J$2*100 -> 116.43738 | L14: =(D14-D13)/D13*100 -> 0.70699778 | M14: {=TREND($D$2:$D$26,$A$2:$A$26,A14)} -> 2748979.1 | N14: =(D14-M14)/M14*100 -> -0.73257973 | O14: =(E14-E13)/E13*100 -> 2.0084896 | P14: =(H14-H13)/H13*100 -> 1.4327479 | Q14: =B14-B13 -> -0.4 | R14: =AVERAGE($B$2:$B$26) -> 6.024 | S14: =B14-R14 -> -0.924
... A26: 45292 | B26: 3.4 | C26: 4389409 | D26: 3091433.5 | E26: 125.81121 | F26: 83516593 | H26: =C26/D26*100 -> 141.9862 | I26: =H26/$H$2*100 -> 159.71769 | J26: =(D26*1000000)/F26 -> 37015.8 | K26: =J26/$J$2*100 -> 127.02725 | L26: =(D26-D25)/D25*100 -> 0.040531606 | M26: {=TREND($D$2:$D$26,$A$2:$A$26,A26)} -> 3151345.2 | N26: =(D26-M26)/M26*100 -> -1.901148 | O26: =(E26-E25)/E25*100 -> 2.2564933 | P26: =(H26-H25)/H25*100 -> 3.092413 | Q26: =B26-B25 -> 0.3 | R26: =AVERAGE($B$2:$B$26) -> 6.024 | S26: =B26-R26 -> -2.624
A27: Data Sources | B27: FRED `LRHUTTTTDEM156S` | C27: FRED `CPMNACSCAB1GQDE` | D27: FRED `CLVMNACSCAB1GQDE` | E27: FRED `DEUCPIALLMINMEI` | F27: FRED `POPTOTDEA647NWDB` | H27: Excel formula | I27: Excel formula | J27: Excel formula | K27: Excel formula | L27: Excel formula | M27: Excel formula | N27: Excel formula | O27: Excel formula | P27: Excel formula | Q27: Excel formula | R27: Excel formula | S27: Excel formula
H28: Nominal GDP / Real GDP × 100 | I28: GDP Deflator / GDP Deflator in 2000 × 100 | J28: (Real GDP × 1,000,000) / Population → EUR/person | K28: Real GDP per Capita / 2000 value × 100 | L28: (Real GDP_t − Real GDP_t−1) / Real GDP_t−1 × 100 | M28: TREND(Real GDP 2000–2024, time 2000–2024) | N28: (Actual Real GDP − Potential GDP) / Potential GDP × 100 | O28: (CPI_t − CPI_t−1) / CPI_t−1 × 100 | P28: (Deflator_t − Deflator_t−1) / Deflator_t−1 × 100 | Q28: Unemployment_t − Unemployment_t−1 | R28: AVERAGE(Unemployment, 2000–2024) | S28: Actual unemployment − full-sample average
A29: sample period | B29: 2000–2024 | C29: 2000–2024 | D29: 2000–2024 | E29: 2000–2024 | F29: 2000–2024 | G29: valid | H29: 2000–2024 | I29: 2000–2024 | J29: 2000–2024 | K29: 2000–2024 | L29: 2001–2024 | M29: 2000–2024 | N29: 2000–2024 | O29: 2001–2024 | P29: 2001–2024 | Q29: 2001–2024 | R29: 2000–2024 | S29: 2000–2024
A30: type | B30: Monthly harmonized unemployment rate (%) | C30: Quarterly nominal GDP (million EUR) | D30: Quarterly real GDP (million chained EUR) | E30: Monthly CPI index (2015 = 100) | F30: Annual population (persons) | G30: inputs | H30: C, D | I30: H | J30: D, F | K30: J | L30: D | M30: A, D | N30: D, M | O30: E | P30: H | Q30: B | R30: B | S30: B, R
A31: Data processing | B31: Converted to annual using the annual average. | C31: Four quarterly values were summed to obtain each annual GDP value. | D31: Four quarterly values were summed to obtain each annual real GDP value. | E31: Converted to annual using the annual average. | F31: Already annual; no frequency conversion. | G31: purpose | H31: Implicit price index for domestic output. | I31: Re-bases each country's deflator so 2000 = 100 for comparison. | J31: Converts GDP from millions of EUR to EUR before dividing by persons. | K31: Measures cumulative real-GDP-per-capita growth since 2000. | L31: Year-over-year real output growth. | M31: Full-sample linear trend used as the homework proxy for potential GDP. | N31: Measures actual output relative to the linear-trend proxy. | O31: Annual CPI inflation. | P31: Annual inflation implied by the GDP deflator. | Q31: Percentage-point change in unemployment; used in Okun scatter plot. | R31: Simple benchmark for the 'normal' unemployment rate in Q9. | S31: Positive values mean unemployment is above its 2000–2024 average.

Sheet China
A1: Year | B1: Youth Unemployment Rate (%) | C1: Nominal GDP (million yuan) | D1: Real GDP - Reconstructed (million yuan, base 2000) | E1: CPI (2015=100) | F1: Population (persons) | G1: Real GDP Growth Input (%) | I1: GDP Deflator | J1: GDP Deflator Index (2000=100) | K1: Real GDP per Capita (Yuan/person) | L1: Real GDP per Capita Index (2000=100) | M1: Real GDP Growth (%) | N1: Potential GDP (Linear Trend) | O1: Output Gap (%) | P1: CPI Inflation Rate (%) | Q1: GDP Deflator Inflation Rate (%) | R1: Change in Unemployment Rate (pp) | S1: Average Unemployment Rate (%) | T1: Unemployment Gap (pp)
A2: 36526 | B2: 6.84 | C2: 10130860 | D2: =C2 -> 10130860 | E2: 70.456424 | F2: 1262645000 | G2: 8.6 | I2: =C2/D2*100 -> 100 | J2: =I2/$I$2*100 -> 100 | K2: =(D2*1000000)/F2 -> 8023.5221 | L2: =K2/$K$2*100 -> 100 | N2: {=TREND($D$2:$D$26,$A$2:$A$26,A2)} -> 5169482.5 | O2: =(D2-N2)/N2*100 -> 95.974353 | S2: =AVERAGE($B$2:$B$26) -> 10.55848 | T2: =B2-S2 -> -3.71848
A3: 36892 | B3: 7.994 | C3: 11215730 | D3: =D2*(1+G3/100) -> 10971721 | E3: 70.963099 | F3: 1271850000 | G3: 8.3 | I3: =C3/D3*100 -> 102.22398 | J3: =I3/$I$2*100 -> 102.22398 | K3: =(D3*1000000)/F3 -> 8626.5844 | L3: =K3/$K$2*100 -> 107.51618 | M3: =(D3-D2)/D2*100 -> 8.3 | N3: {=TREND($D$2:$D$26,$A$2:$A$26,A3)} -> 7614700.5 | O3: =(D3-N3)/N3*100 -> 44.086052 | P3: =(E3-E2)/E2*100 -> 0.71913244 | Q3: =(I3-I2)/I2*100 -> 2.2239775 | R3: =B3-B2 -> 1.154 | S3: =AVERAGE($B$2:$B$26) -> 10.55848 | T3: =B3-S3 -> -2.56448
A4: 37257 | B4: 8.919 | C4: 12331180 | D4: =D3*(1+G4/100) -> 11981120 | E4: 70.443667 | F4: 1280400000 | G4: 9.2 | I4: =C4/D4*100 -> 102.92177 | J4: =I4/$I$2*100 -> 102.92177 | K4: =(D4*1000000)/F4 -> 9357.3256 | L4: =K4/$K$2*100 -> 116.62367 | M4: =(D4-D3)/D3*100 -> 9.2 | N4: {=TREND($D$2:$D$26,$A$2:$A$26,A4)} -> 10053238 | O4: =(D4-N4)/N4*100 -> 19.176729 | P4: =(E4-E3)/E3*100 -> -0.7319755 | Q4: =(I4-I3)/I3*100 -> 0.68260717 | R4: =B4-B3 -> 0.925 | S4: =AVERAGE($B$2:$B$26) -> 10.55848 | T4: =B4-S4 -> -1.63948
A5: 37622 | B5: 9.624 | C5: 13937730 | D5: =D4*(1+G5/100) -> 13191213 | E5: 71.237991 | F5: 1288400000 | G5: 10.1 | I5: =C5/D5*100 -> 105.6592 | J5: =I5/$I$2*100 -> 105.6592 | K5: =(D5*1000000)/F5 -> 10238.445 | L5: =K5/$K$2*100 -> 127.60537 | M5: =(D5-D4)/D4*100 -> 10.1 | N5: {=TREND($D$2:$D$26,$A$2:$A$26,A5)} -> 12491775 | O5: =(D5-N5)/N5*100 -> 5.5991902 | P5: =(E5-E4)/E4*100 -> 1.127602 | Q5: =(I5-I4)/I4*100 -> 2.6597237 | R5: =B5-B4 -> 0.705 | S5: =AVERAGE($B$2:$B$26) -> 10.55848 | T5: =B5-S5 -> -0.93448
A6: 37987 | B6: 9.433 | C6: 16422790 | D6: =D5*(1+G6/100) -> 14523525 | E6: 73.962586 | F6: 1296075000 | G6: 10.1 | I6: =C6/D6*100 -> 113.07716 | J6: =I6/$I$2*100 -> 113.07716 | K6: =(D6*1000000)/F6 -> 11205.775 | L6: =K6/$K$2*100 -> 139.66155 | M6: =(D6-D5)/D5*100 -> 10.1 | N6: {=TREND($D$2:$D$26,$A$2:$A$26,A6)} -> 14930312 | O6: =(D6-N6)/N6*100 -> -2.7245669 | P6: =(E6-E5)/E5*100 -> 3.8246376 | Q6: =(I6-I5)/I5*100 -> 7.0206473 | R6: =B6-B5 -> -0.191 | S6: =AVERAGE($B$2:$B$26) -> 10.55848 | T6: =B6-S6 -> -1.12548
A7: 38353 | B7: 9.495 | C7: 18990750 | D7: =D6*(1+G7/100) -> 16193731 | E7: 75.276469 | F7: 1303720000 | G7: 11.5 | I7: =C7/D7*100 -> 117.27224 | J7: =I7/$I$2*100 -> 117.27224 | K7: =(D7*1000000)/F7 -> 12421.172 | L7: =K7/$K$2*100 -> 154.80947 | M7: =(D7-D6)/D6*100 -> 11.5 | N7: {=TREND($D$2:$D$26,$A$2:$A$26,A7)} -> 17375530 | O7: =(D7-N7)/N7*100 -> -6.8015129 | P7: =(E7-E6)/E6*100 -> 1.7764162 | Q7: =(I7-I6)/I6*100 -> 3.7099225 | R7: =B7-B6 -> 0.062 | S7: =AVERAGE($B$2:$B$26) -> 10.55848 | T7: =B7-S7 -> -1.06348
A8: 38718 | B8: 9.331 | C8: 22257830 | D8: =D7*(1+G8/100) -> 18250335 | E8: 76.518104 | F8: 1311020000 | G8: 12.7 | I8: =C8/D8*100 -> 121.95848 | J8: =I8/$I$2*100 -> 121.95848 | K8: =(D8*1000000)/F8 -> 13920.714 | L8: =K8/$K$2*100 -> 173.49879 | M8: =(D8-D7)/D7*100 -> 12.7 | N8: {=TREND($D$2:$D$26,$A$2:$A$26,A8)} -> 19814067 | O8: =(D8-N8)/N8*100 -> -7.8920303 | P8: =(E8-E7)/E7*100 -> 1.6494331 | Q8: =(I8-I7)/I7*100 -> 3.9960366 | R8: =B8-B7 -> -0.164 | S8: =AVERAGE($B$2:$B$26) -> 10.55848 | T8: =B8-S8 -> -1.22748
A9: 39083 | B9: 9.224 | C9: 27417970 | D9: =D8*(1+G9/100) -> 20841882 | E9: 80.203802 | F9: 1317885000 | G9: 14.2 | I9: =C9/D9*100 -> 131.55227 | J9: =I9/$I$2*100 -> 131.55227 | K9: =(D9*1000000)/F9 -> 15814.644 | L9: =K9/$K$2*100 -> 197.10351 | M9: =(D9-D8)/D8*100 -> 14.2 | N9: {=TREND($D$2:$D$26,$A$2:$A$26,A9)} -> 22252604 | O9: =(D9-N9)/N9*100 -> -6.3395803 | P9: =(E9-E8)/E8*100 -> 4.8167653 | Q9: =(I9-I8)/I8*100 -> 7.8664465 | R9: =B9-B8 -> -0.107 | S9: =AVERAGE($B$2:$B$26) -> 10.55848 | T9: =B9-S9 -> -1.33448
A10: 39448 | B10: 9.803 | C10: 32431790 | D10: =D9*(1+G10/100) -> 22863545 | E10: 84.956082 | F10: 1324655000 | G10: 9.7 | I10: =C10/D10*100 -> 141.84935 | J10: =I10/$I$2*100 -> 141.84935 | K10: =(D10*1000000)/F10 -> 17259.999 | L10: =K10/$K$2*100 -> 215.11749 | M10: =(D10-D9)/D9*100 -> 9.7 | N10: {=TREND($D$2:$D$26,$A$2:$A$26,A10)} -> 24691141 | O10: =(D10-N10)/N10*100 -> -7.4018296 | P10: =(E10-E9)/E9*100 -> 5.9252553 | Q10: =(I10-I9)/I9*100 -> 7.8273656 | R10: =B10-B9 -> 0.579 | S10: =AVERAGE($B$2:$B$26) -> 10.55848 | T10: =B10-S10 -> -0.75548
A11: 39814 | B11: 10.15 | C11: 35452160 | D11: =D10*(1+G11/100) -> 25012718 | E11: 84.337456 | F11: 1331260000 | G11: 9.4 | I11: =C11/D11*100 -> 141.73654 | J11: =I11/$I$2*100 -> 141.73654 | K11: =(D11*1000000)/F11 -> 18788.755 | L11: =K11/$K$2*100 -> 234.17091 | M11: =(D11-D10)/D10*100 -> 9.4 | N11: {=TREND($D$2:$D$26,$A$2:$A$26,A11)} -> 27136359 | O11: =(D11-N11)/N11*100 -> -7.825814 | P11: =(E11-E10)/E10*100 -> -0.72817133 | Q11: =(I11-I10)/I10*100 -> -0.079532016 | R11: =B11-B10 -> 0.347 | S11: =AVERAGE($B$2:$B$26) -> 10.55848 | T11: =B11-S11 -> -0.40848
A12: 40179 | B12: 9.823 | C12: 41925330 | D12: =D11*(1+G12/100) -> 27664066 | E12: 87.015447 | F12: 1337705000 | G12: 10.6 | I12: =C12/D12*100 -> 151.55158 | J12: =I12/$I$2*100 -> 151.55158 | K12: =(D12*1000000)/F12 -> 20680.244 | L12: =K12/$K$2*100 -> 257.74521 | M12: =(D12-D11)/D11*100 -> 10.6 | N12: {=TREND($D$2:$D$26,$A$2:$A$26,A12)} -> 29574896 | O12: =(D12-N12)/N12*100 -> -6.4609861 | P12: =(E12-E11)/E11*100 -> 3.175328 | Q12: =(I12-I11)/I11*100 -> 6.924853 | R12: =B12-B11 -> -0.327 | S12: =AVERAGE($B$2:$B$26) -> 10.55848 | T12: =B12-S12 -> -0.73548
A13: 40544 | B13: 9.976 | C13: 49570750 | D13: =D12*(1+G13/100) -> 30292152 | E13: 91.848195 | F13: 1345035000 | G13: 9.5 | I13: =C13/D13*100 -> 163.64222 | J13: =I13/$I$2*100 -> 163.64222 | K13: =(D13*1000000)/F13 -> 22521.46 | L13: =K13/$K$2*100 -> 280.69294 | M13: =(D13-D12)/D12*100 -> 9.5 | N13: {=TREND($D$2:$D$26,$A$2:$A$26,A13)} -> 32013433 | O13: =(D13-N13)/N13*100 -> -5.3767452 | P13: =(E13-E12)/E12*100 -> 5.5538971 | Q13: =(I13-I12)/I12*100 -> 7.977901 | R13: =B13-B12 -> 0.153 | S13: =AVERAGE($B$2:$B$26) -> 10.55848 | T13: =B13-S13 -> -0.58248
A14: 40909 | B14: 10.154 | C14: 54751070 | D14: =D13*(1+G14/100) -> 32685232 | E14: 94.254182 | F14: 1354190000 | G14: 7.9 | I14: =C14/D14*100 -> 167.51011 | J14: =I14/$I$2*100 -> 167.51011 | K14: =(D14*1000000)/F14 -> 24136.371 | L14: =K14/$K$2*100 -> 300.82015 | M14: =(D14-D13)/D13*100 -> 7.9 | N14: {=TREND($D$2:$D$26,$A$2:$A$26,A14)} -> 34451970 | O14: =(D14-N14)/N14*100 -> -5.1281182 | P14: =(E14-E13)/E13*100 -> 2.6195262 | Q14: =(I14-I13)/I13*100 -> 2.3636296 | R14: =B14-B13 -> 0.178 | S14: =AVERAGE($B$2:$B$26) -> 10.55848 | T14: =B14-S14 -> -0.40448
... A26: 45292 | B26: 15.044 | C26: 134806620 | D26: =D25*(1+G26/100) -> 66464877 | E26: 115.31077 | F26: 1408975000 | G26: 5 | I26: =C26/D26*100 -> 202.82385 | J26: =I26/$I$2*100 -> 202.82385 | K26: =(D26*1000000)/F26 -> 47172.503 | L26: =K26/$K$2*100 -> 587.92763 | M26: =(D26-D25)/D25*100 -> 5 | N26: {=TREND($D$2:$D$26,$A$2:$A$26,A26)} -> 63734457 | O26: =(D26-N26)/N26*100 -> 4.2840559 | P26: =(E26-E25)/E25*100 -> 0.21812572 | Q26: =(I26-I25)/I25*100 -> -0.80348104 | R26: =B26-B25 -> -0.518 | S26: =AVERAGE($B$2:$B$26) -> 10.55848 | T26: =B26-S26 -> 4.48552
A27: Data Sources | B27: FRED `SLUEM1524ZSCHN` | C27: FRED `NGDPXDCCNA` | D27: Reconstructed from FRED `CHNGDPRAPSMEI` | E27: FRED `CHNCPIALLMINMEI` | F27: FRED `POPTOTCNA647NWDB` | G27: FRED `CHNGDPRAPSMEI` | I27: Excel formula | J27: Excel formula | K27: Excel formula | L27: Excel formula | M27: Excel formula | N27: Excel formula | O27: Excel formula | P27: Excel formula | Q27: Excel formula | R27: Excel formula | S27: Excel formula | T27: Excel formula
I28: Nominal GDP / Reconstructed Real GDP × 100 | J28: GDP Deflator / GDP Deflator in 2000 × 100 | K28: (Reconstructed Real GDP × 1,000,000) / Population → Yuan/person | L28: Real GDP per Capita / 2000 value × 100 | M28: (Real GDP_t − Real GDP_t−1) / Real GDP_t−1 × 100 | N28: TREND(Reconstructed Real GDP 2000–2024, time 2000–2024) | O28: (Actual Real GDP − Potential GDP) / Potential GDP × 100 | P28: (CPI_t − CPI_t−1) / CPI_t−1 × 100 | Q28: (Deflator_t − Deflator_t−1) / Deflator_t−1 × 100 | R28: Youth unemployment_t − Youth unemployment_t−1 | S28: AVERAGE(Youth unemployment, 2000–2024) | T28: Actual youth unemployment − full-sample average
A29: sample period | B29: 2000–2024 | C29: 2000–2024 | D29: 2000–2024 | E29: 2000–2024 | F29: 2000–2024 | G29: 2000–2024 | H29: valid | I29: 2000–2024 | J29: 2000–2024 | K29: 2000–2024 | L29: 2000–2024 | M29: 2001–2024 | N29: 2000–2024 | O29: 2000–2024 | P29: 2001–2024 | Q29: 2001–2024 | R29: 2001–2024 | S29: 2000–2024 | T29: 2000–2024
A30: type | B30: Annual youth unemployment rate, ages 15–24 (%) | C30: Annual nominal GDP (million yuan) | D30: Reconstructed real GDP level | E30: Monthly CPI index (2015 = 100) | F30: Annual population (persons) | G30: Annual real GDP growth rate (%) | H30: inputs | I30: C, D | J30: I | K30: D, F | L30: K | M30: D | N30: A, D | O30: D, N | P30: E | Q30: I | R30: B | S30: B | T30: B, S
A31: Data processing | B31: Already annual; no frequency conversion. | C31: Already annual; no frequency conversion. | D31: 2000 was used as the base/start value; later real GDP values were chained using the annual real GDP growth rate. | E31: Converted to annual using the annual average. | F31: Already annual; no frequency conversion. | G31: Already annual; used as the input for real GDP reconstruction. | H31: purpose | I31: Implicit price index based on the reconstructed real-GDP series. | J31: Re-bases the deflator so 2000 = 100 for comparison. | K31: Converts GDP from million yuan to yuan before dividing by persons. | L31: Measures cumulative real-GDP-per-capita growth since 2000. | M31: Year-over-year growth of the reconstructed real-GDP series. | N31: Full-sample linear trend used as the homework proxy for potential GDP. | O31: Measures actual output relative to the linear-trend proxy. | P31: Annual CPI inflation. | Q31: Annual inflation implied by the reconstructed GDP deflator. | R31: Percentage-point change in the selected youth-unemployment series. | S31: Simple benchmark for the selected unemployment series in Q9. | T31: Positive values mean youth unemployment is above its sample average.

Sheet Italy
A1: Year | B1: Unemployment rate | C1: Nominal GDP | D1: Real GDP | E1: CPI( base = 2015) | F1: Population(person) | H1: GDP Deflator | I1: GDP Deflator Index (2000=100) | J1: Real GDP per Capita (EUR/person) | K1: Real GDP per Capita Index (2000=100) | L1: Real GDP Growth (%) | M1: Potential GDP (Linear Trend) | N1: Output Gap (%) | O1: CPI Inflation Rate (%) | P1: GDP Deflator Inflation Rate (%) | Q1: Change in Unemployment Rate (pp) | R1: Average Unemployment Rate (%) | S1: Unemployment Gap (pp)
A2: 36526 | B2: 10.1 | C2: 1245557 | D2: 1573989 | E2: 75.057391 | F2: 56942108 | H2: =C2/D2*100 -> 79.13378 | I2: =H2/$H$2*100 -> 100 | J2: =(D2*1000000)/F2 -> 27641.917 | K2: =J2/$J$2*100 -> 100 | M2: {=TREND($D$2:$D$26,$A$2:$A$26,A2)} -> 1609949.5 | N2: =(D2-M2)/M2*100 -> -2.2336395 | R2: =AVERAGE($B$2:$B$26) -> 9.2 | S2: =B2-R2 -> 0.9
A3: 36892 | B3: 9.1 | C3: 1307586 | D3: 1603251.6 | E3: 77.147863 | F3: 56976981 | H3: =C3/D3*100 -> 81.558378 | I3: =H3/$H$2*100 -> 103.06392 | J3: =(D3*1000000)/F3 -> 28138.585 | K3: =J3/$J$2*100 -> 101.79679 | L3: =(D3-D2)/D2*100 -> 1.8591362 | M3: {=TREND($D$2:$D$26,$A$2:$A$26,A3)} -> 1610755.6 | N3: =(D3-M3)/M3*100 -> -0.46586673 | O3: =(E3-E2)/E2*100 -> 2.7851654 | P3: =(H3-H2)/H2*100 -> 3.0639223 | Q3: =B3-B2 -> -1 | R3: =AVERAGE($B$2:$B$26) -> 9.2 | S3: =B3-R3 -> -0.1
A4: 37257 | B4: 8.6 | C4: 1354153 | D4: 1607214.9 | E4: 79.049808 | F4: 57089824 | H4: =C4/D4*100 -> 84.254632 | I4: =H4/$H$2*100 -> 106.47113 | J4: =(D4*1000000)/F4 -> 28152.388 | K4: =J4/$J$2*100 -> 101.84673 | L4: =(D4-D3)/D3*100 -> 0.24720387 | M4: {=TREND($D$2:$D$26,$A$2:$A$26,A4)} -> 1611559.5 | N4: =(D4-M4)/M4*100 -> -0.26958847 | O4: =(E4-E3)/E3*100 -> 2.4653232 | P4: =(H4-H3)/H3*100 -> 3.3059192 | Q4: =B4-B3 -> -0.5 | R4: =AVERAGE($B$2:$B$26) -> 9.2 | S4: =B4-R4 -> -0.6
A5: 37622 | B5: 8.5 | C5: 1399084 | D5: 1609558.9 | E5: 81.162458 | F5: 57399184 | H5: =C5/D5*100 -> 86.923442 | I5: =H5/$H$2*100 -> 109.84366 | J5: =(D5*1000000)/F5 -> 28041.494 | K5: =J5/$J$2*100 -> 101.44555 | L5: =(D5-D4)/D4*100 -> 0.14584235 | M5: {=TREND($D$2:$D$26,$A$2:$A$26,A5)} -> 1612363.4 | N5: =(D5-M5)/M5*100 -> -0.17393616 | O5: =(E5-E4)/E4*100 -> 2.6725555 | P5: =(H5-H4)/H4*100 -> 3.167553 | Q5: =B5-B4 -> -0.1 | R5: =AVERAGE($B$2:$B$26) -> 9.2 | S5: =B5-R5 -> -0.7
A6: 37987 | B6: 8 | C6: 1453947 | D6: 1629745.2 | E6: 82.953499 | F6: 57828179 | H6: =C6/D6*100 -> 89.213148 | I6: =H6/$H$2*100 -> 112.73712 | J6: =(D6*1000000)/F6 -> 28182.544 | K6: =J6/$J$2*100 -> 101.95582 | L6: =(D6-D5)/D5*100 -> 1.2541511 | M6: {=TREND($D$2:$D$26,$A$2:$A$26,A6)} -> 1613167.3 | N6: =(D6-M6)/M6*100 -> 1.0276623 | O6: =(E6-E5)/E5*100 -> 2.2067366 | P6: =(H6-H5)/H5*100 -> 2.6341639 | Q6: =B6-B5 -> -0.5 | R6: =AVERAGE($B$2:$B$26) -> 9.2 | S6: =B6-R6 -> -1.2
A7: 38353 | B7: 7.8 | C7: 1501176 | D7: 1648378.7 | E7: 84.600369 | F7: 58166682 | H7: =C7/D7*100 -> 91.069849 | I7: =H7/$H$2*100 -> 115.08341 | J7: =(D7*1000000)/F7 -> 28338.881 | K7: =J7/$J$2*100 -> 102.52141 | L7: =(D7-D6)/D6*100 -> 1.1433382 | M7: {=TREND($D$2:$D$26,$A$2:$A$26,A7)} -> 1613973.4 | N7: =(D7-M7)/M7*100 -> 2.1317146 | O7: =(E7-E6)/E6*100 -> 1.985293 | P7: =(H7-H6)/H6*100 -> 2.0811969 | Q7: =B7-B6 -> -0.2 | R7: =AVERAGE($B$2:$B$26) -> 9.2 | S7: =B7-R7 -> -1.4
A8: 38718 | B8: 6.9 | C8: 1563447 | D8: 1679634.6 | E8: 86.369231 | F8: 58399861 | H8: =C8/D8*100 -> 93.082567 | I8: =H8/$H$2*100 -> 117.62684 | J8: =(D8*1000000)/F8 -> 28760.935 | K8: =J8/$J$2*100 -> 104.04827 | L8: =(D8-D7)/D7*100 -> 1.8961601 | M8: {=TREND($D$2:$D$26,$A$2:$A$26,A8)} -> 1614777.3 | N8: =(D8-M8)/M8*100 -> 4.0164858 | O8: =(E8-E7)/E7*100 -> 2.0908439 | P8: =(H8-H7)/H7*100 -> 2.210081 | Q8: =B8-B7 -> -0.9 | R8: =AVERAGE($B$2:$B$26) -> 9.2 | S8: =B8-R8 -> -2.3
A9: 39083 | B9: 6.2 | C9: 1622562 | D9: 1701173.5 | E9: 87.949564 | F9: 58756247 | H9: =C9/D9*100 -> 95.378984 | I9: =H9/$H$2*100 -> 120.52878 | J9: =(D9*1000000)/F9 -> 28953.066 | K9: =J9/$J$2*100 -> 104.74334 | L9: =(D9-D8)/D8*100 -> 1.2823563 | M9: {=TREND($D$2:$D$26,$A$2:$A$26,A9)} -> 1615581.2 | N9: =(D9-M9)/M9*100 -> 5.297926 | O9: =(E9-E8)/E8*100 -> 1.8297411 | P9: =(H9-H8)/H8*100 -> 2.4670754 | Q9: =B9-B8 -> -0.7 | R9: =AVERAGE($B$2:$B$26) -> 9.2 | S9: =B9-R9 -> -3
A10: 39448 | B10: 6.8 | C10: 1643974 | D10: 1683152 | E10: 90.893968 | F10: 59211181 | H10: =C10/D10*100 -> 97.672343 | I10: =H10/$H$2*100 -> 123.42686 | J10: =(D10*1000000)/F10 -> 28426.253 | K10: =J10/$J$2*100 -> 102.83749 | L10: =(D10-D9)/D9*100 -> -1.059357 | M10: {=TREND($D$2:$D$26,$A$2:$A$26,A10)} -> 1616385.1 | N10: =(D10-M10)/M10*100 -> 4.1306303 | O10: =(E10-E9)/E9*100 -> 3.3478326 | P10: =(H10-H9)/H9*100 -> 2.4044703 | Q10: =B10-B9 -> 0.6 | R10: =AVERAGE($B$2:$B$26) -> 9.2 | S10: =B10-R10 -> -2.4
A11: 39814 | B11: 7.9 | C11: 1584007 | D11: 1593498 | E11: 91.598186 | F11: 59555454 | H11: =C11/D11*100 -> 99.404392 | I11: =H11/$H$2*100 -> 125.61562 | J11: =(D11*1000000)/F11 -> 26756.542 | K11: =J11/$J$2*100 -> 96.796985 | L11: =(D11-D10)/D10*100 -> -5.326554 | M11: {=TREND($D$2:$D$26,$A$2:$A$26,A11)} -> 1617191.2 | N11: =(D11-M11)/M11*100 -> -1.4650843 | O11: =(E11-E10)/E10*100 -> 0.77476813 | P11: =(H11-H10)/H10*100 -> 1.7733257 | Q11: =B11-B10 -> 1.1 | R11: =AVERAGE($B$2:$B$26) -> 9.2 | S11: =B11-R11 -> -1.3
A12: 40179 | B12: 8.5 | C12: 1617083 | D12: 1617083.2 | E12: 92.995531 | F12: 59819407 | H12: =C12/D12*100 -> 99.999988 | I12: =H12/$H$2*100 -> 126.36827 | J12: =(D12*1000000)/F12 -> 27032.752 | K12: =J12/$J$2*100 -> 97.796229 | L12: =(D12-D11)/D11*100 -> 1.4800897 | M12: {=TREND($D$2:$D$26,$A$2:$A$26,A12)} -> 1617995.1 | N12: =(D12-M12)/M12*100 -> -0.056361011 | O12: =(E12-E11)/E11*100 -> 1.525516 | P12: =(H12-H11)/H11*100 -> 0.5991642 | Q12: =B12-B11 -> 0.6 | R12: =AVERAGE($B$2:$B$26) -> 9.2 | S12: =B12-R12 -> -0.7
A13: 40544 | B13: 8.6 | C13: 1659112 | D13: 1630941 | E13: 95.581395 | F13: 60026841 | H13: =C13/D13*100 -> 101.72729 | I13: =H13/$H$2*100 -> 128.55102 | J13: =(D13*1000000)/F13 -> 27170.195 | K13: =J13/$J$2*100 -> 98.293457 | L13: =(D13-D12)/D12*100 -> 0.85696271 | M13: {=TREND($D$2:$D$26,$A$2:$A$26,A13)} -> 1618799 | N13: =(D13-M13)/M13*100 -> 0.75006082 | O13: =(E13-E12)/E12*100 -> 2.7806327 | P13: =(H13-H12)/H12*100 -> 1.7272976 | Q13: =B13-B12 -> 0.1 | R13: =AVERAGE($B$2:$B$26) -> 9.2 | S13: =B13-R13 -> -0.6
A14: 40909 | B14: 10.9 | C14: 1633776 | D14: 1579157.7 | E14: 98.488372 | F14: 60191247 | H14: =C14/D14*100 -> 103.4587 | I14: =H14/$H$2*100 -> 130.73898 | J14: =(D14*1000000)/F14 -> 26235.67 | K14: =J14/$J$2*100 -> 94.91263 | L14: =(D14-D13)/D13*100 -> -3.1750566 | M14: {=TREND($D$2:$D$26,$A$2:$A$26,A14)} -> 1619602.9 | N14: =(D14-M14)/M14*100 -> -2.497231 | O14: =(E14-E13)/E13*100 -> 3.0413633 | P14: =(H14-H13)/H13*100 -> 1.7020146 | Q14: =B14-B13 -> 2.3 | R14: =AVERAGE($B$2:$B$26) -> 9.2 | S14: =B14-R14 -> 1.7
... A26: 45292 | B26: 6.6 | C26: 2199105 | D26: 1721090.6 | E26: 120.78333 | F26: 58952704 | H26: =C26/D26*100 -> 127.77392 | I26: =H26/$H$2*100 -> 161.46571 | J26: =(D26*1000000)/F26 -> 29194.43 | K26: =J26/$J$2*100 -> 105.61652 | L26: =(D26-D25)/D25*100 -> 0.58635074 | M26: {=TREND($D$2:$D$26,$A$2:$A$26,A26)} -> 1629256.4 | N26: =(D26-M26)/M26*100 -> 5.6365722 | O26: =(E26-E25)/E25*100 -> 0.98237302 | P26: =(H26-H25)/H25*100 -> 1.970949 | Q26: =B26-B25 -> -1.1 | R26: =AVERAGE($B$2:$B$26) -> 9.2 | S26: =B26-R26 -> -2.6
A27: Data Sources | B27: FRED `LRHUTTTTITM156S` | C27: FRED `CPMNACSCAB1GQIT` | D27: FRED `CLVMNACSCAB1GQIT` | E27: FRED `ITACPIALLMINMEI` | F27: FRED `POPTOTITA647NWDB` | H27: Excel formula | I27: Excel formula | J27: Excel formula | K27: Excel formula | L27: Excel formula | M27: Excel formula | N27: Excel formula | O27: Excel formula | P27: Excel formula | Q27: Excel formula | R27: Excel formula | S27: Excel formula
H28: Nominal GDP / Real GDP × 100 | I28: GDP Deflator / GDP Deflator in 2000 × 100 | J28: (Real GDP × 1,000,000) / Population → EUR/person | K28: Real GDP per Capita / 2000 value × 100 | L28: (Real GDP_t − Real GDP_t−1) / Real GDP_t−1 × 100 | M28: TREND(Real GDP 2000–2024, time 2000–2024) | N28: (Actual Real GDP − Potential GDP) / Potential GDP × 100 | O28: (CPI_t − CPI_t−1) / CPI_t−1 × 100 | P28: (Deflator_t − Deflator_t−1) / Deflator_t−1 × 100 | Q28: Unemployment_t − Unemployment_t−1 | R28: AVERAGE(Unemployment, 2000–2024) | S28: Actual unemployment − full-sample average
A29: sample period | B29: 2000–2024 | C29: 2000–2024 | D29: 2000–2024 | E29: 2000–2024 | F29: 2000–2024 | G29: valid | H29: 2000–2024 | I29: 2000–2024 | J29: 2000–2024 | K29: 2000–2024 | L29: 2001–2024 | M29: 2000–2024 | N29: 2000–2024 | O29: 2001–2024 | P29: 2001–2024 | Q29: 2001–2024 | R29: 2000–2024 | S29: 2000–2024
A30: type | B30: Monthly harmonized unemployment rate (%) | C30: Quarterly nominal GDP (million EUR) | D30: Quarterly real GDP (million chained EUR) | E30: Monthly CPI index (2015 = 100) | F30: Annual population (persons) | G30: inputs | H30: C, D | I30: H | J30: D, F | K30: J | L30: D | M30: A, D | N30: D, M | O30: E | P30: H | Q30: B | R30: B | S30: B, R
A31: Data processing | B31: Converted to annual using the annual average. | C31: Four quarterly values were summed to obtain each annual GDP value. | D31: Four quarterly values were summed to obtain each annual real GDP value. | E31: Converted to annual using the annual average. | F31: Already annual; no frequency conversion. | G31: purpose | H31: Implicit price index for domestic output. | I31: Re-bases each country's deflator so 2000 = 100 for comparison. | J31: Converts GDP from millions of EUR to EUR before dividing by persons. | K31: Measures cumulative real-GDP-per-capita growth since 2000. | L31: Year-over-year real output growth. | M31: Full-sample linear trend used as the homework proxy for potential GDP. | N31: Measures actual output relative to the linear-trend proxy. | O31: Annual CPI inflation. | P31: Annual inflation implied by the GDP deflator. | Q31: Percentage-point change in unemployment; used in Okun scatter plot. | R31: Simple benchmark for the 'normal' unemployment rate in Q9. | S31: Positive values mean unemployment is above its 2000–2024 average.

Sheet France
A1: Year | B1: Unemployment rate | C1: Nominal GDP | D1: Real GDP | E1: CPI( base = 2015) | F1: Population(person) | H1: GDP Deflator | I1: GDP Deflator Index (2000=100) | J1: Real GDP per Capita (EUR/person) | K1: Real GDP per Capita Index (2000=100) | L1: Real GDP Growth (%) | M1: Potential GDP (Linear Trend) | N1: Output Gap (%) | O1: CPI Inflation Rate (%) | P1: GDP Deflator Inflation Rate (%) | Q1: Change in Unemployment Rate (pp) | R1: Average Unemployment Rate (%) | S1: Unemployment Gap (pp)
A2: 36526 | B2: 9.2 | C2: 1475503.3 | D2: 1750227.2 | E2: 79.929167 | F2: 60918661 | H2: =C2/D2*100 -> 84.303529 | I2: =H2/$H$2*100 -> 100 | J2: =(D2*1000000)/F2 -> 28730.559 | K2: =J2/$J$2*100 -> 100 | M2: {=TREND($D$2:$D$26,$A$2:$A$26,A2)} -> 1778794.2 | N2: =(D2-M2)/M2*100 -> -1.6059782 | R2: =AVERAGE($B$2:$B$26) -> 8.792 | S2: =B2-R2 -> 0.408
A3: 36892 | B3: 8.5 | C3: 1531244.5 | D3: 1782380.2 | E3: 81.235833 | F3: 61364377 | H3: =C3/D3*100 -> 85.910094 | I3: =H3/$H$2*100 -> 101.90569 | J3: =(D3*1000000)/F3 -> 29045.845 | K3: =J3/$J$2*100 -> 101.09739 | L3: =(D3-D2)/D2*100 -> 1.8370758 | M3: {=TREND($D$2:$D$26,$A$2:$A$26,A3)} -> 1801425.5 | N3: =(D3-M3)/M3*100 -> -1.0572372 | O3: =(E3-E2)/E2*100 -> 1.6347808 | P3: =(H3-H2)/H2*100 -> 1.9056906 | Q3: =B3-B2 -> -0.7 | R3: =AVERAGE($B$2:$B$26) -> 8.792 | S3: =B3-R3 -> -0.292
A4: 37257 | B4: 8.3 | C4: 1580459.7 | D4: 1802458.8 | E4: 82.798333 | F4: 61812142 | H4: =C4/D4*100 -> 87.683541 | I4: =H4/$H$2*100 -> 104.00934 | J4: =(D4*1000000)/F4 -> 29160.271 | K4: =J4/$J$2*100 -> 101.49566 | L4: =(D4-D3)/D3*100 -> 1.1265049 | M4: {=TREND($D$2:$D$26,$A$2:$A$26,A4)} -> 1823995 | N4: =(D4-M4)/M4*100 -> -1.180716 | O4: =(E4-E3)/E3*100 -> 1.9234123 | P4: =(H4-H3)/H3*100 -> 2.064306 | Q4: =B4-B3 -> -0.2 | R4: =AVERAGE($B$2:$B$26) -> 8.792 | S4: =B4-R4 -> -0.492
A5: 37622 | B5: 8.5 | C5: 1624806.1 | D5: 1820279.2 | E5: 84.535833 | F5: 62249855 | H5: =C5/D5*100 -> 89.261367 | I5: =H5/$H$2*100 -> 105.88094 | J5: =(D5*1000000)/F5 -> 29241.501 | K5: =J5/$J$2*100 -> 101.77839 | L5: =(D5-D4)/D4*100 -> 0.9886717 | M5: {=TREND($D$2:$D$26,$A$2:$A$26,A5)} -> 1846564.5 | N5: =(D5-M5)/M5*100 -> -1.4234683 | O5: =(E5-E4)/E4*100 -> 2.0984722 | P5: =(H5-H4)/H4*100 -> 1.7994554 | Q5: =B5-B4 -> 0.2 | R5: =AVERAGE($B$2:$B$26) -> 8.792 | S5: =B5-R5 -> -0.292
A6: 37987 | B6: 8.9 | C6: 1692878.6 | D6: 1866127.3 | E6: 86.346667 | F6: 62707588 | H6: =C6/D6*100 -> 90.716137 | I6: =H6/$H$2*100 -> 107.60657 | J6: =(D6*1000000)/F6 -> 29759.194 | K6: =J6/$J$2*100 -> 103.58028 | L6: =(D6-D5)/D5*100 -> 2.51874 | M6: {=TREND($D$2:$D$26,$A$2:$A$26,A6)} -> 1869133.9 | N6: =(D6-M6)/M6*100 -> -0.16085625 | O6: =(E6-E5)/E5*100 -> 2.1420896 | P6: =(H6-H5)/H5*100 -> 1.6297868 | Q6: =B6-B5 -> 0.4 | R6: =AVERAGE($B$2:$B$26) -> 8.792 | S6: =B6-R6 -> 0.108
A7: 38353 | B7: 8.9 | C7: 1760519.9 | D7: 1903204.7 | E7: 87.854167 | F7: 63180854 | H7: =C7/D7*100 -> 92.502919 | I7: =H7/$H$2*100 -> 109.72603 | J7: =(D7*1000000)/F7 -> 30123.124 | K7: =J7/$J$2*100 -> 104.84698 | L7: =(D7-D6)/D6*100 -> 1.9868634 | M7: {=TREND($D$2:$D$26,$A$2:$A$26,A7)} -> 1891765.2 | N7: =(D7-M7)/M7*100 -> 0.60469914 | O7: =(E7-E6)/E6*100 -> 1.7458694 | P7: =(H7-H6)/H6*100 -> 1.9696405 | Q7: =B7-B6 -> 0 | R7: =AVERAGE($B$2:$B$26) -> 8.792 | S7: =B7-R7 -> 0.108
A8: 38718 | B8: 8.9 | C8: 1848255.5 | D8: 1959090.6 | E8: 89.325833 | F8: 63622342 | H8: =C8/D8*100 -> 94.342523 | I8: =H8/$H$2*100 -> 111.90815 | J8: =(D8*1000000)/F8 -> 30792.494 | K8: =J8/$J$2*100 -> 107.1768 | L8: =(D8-D7)/D7*100 -> 2.9364104 | M8: {=TREND($D$2:$D$26,$A$2:$A$26,A8)} -> 1914334.7 | N8: =(D8-M8)/M8*100 -> 2.3379365 | O8: =(E8-E7)/E7*100 -> 1.6751245 | P8: =(H8-H7)/H7*100 -> 1.9886984 | Q8: =B8-B7 -> 0 | R8: =AVERAGE($B$2:$B$26) -> 8.792 | S8: =B8-R8 -> 0.108
A9: 39083 | B9: 8 | C9: 1939249.6 | D9: 2007651.7 | E9: 90.655 | F9: 64016890 | H9: =C9/D9*100 -> 96.59293 | I9: =H9/$H$2*100 -> 114.57756 | J9: =(D9*1000000)/F9 -> 31361.281 | K9: =J9/$J$2*100 -> 109.15653 | L9: =(D9-D8)/D8*100 -> 2.4787572 | M9: {=TREND($D$2:$D$26,$A$2:$A$26,A9)} -> 1936904.1 | N9: =(D9-M9)/M9*100 -> 3.6526108 | O9: =(E9-E8)/E8*100 -> 1.4879981 | P9: =(H9-H8)/H8*100 -> 2.385358 | Q9: =B9-B8 -> -0.9 | R9: =AVERAGE($B$2:$B$26) -> 8.792 | S9: =B9-R9 -> -0.792
A10: 39448 | B10: 7.4 | C10: 1989014.9 | D10: 2012887 | E10: 93.205 | F10: 64375116 | H10: =C10/D10*100 -> 98.814037 | I10: =H10/$H$2*100 -> 117.21222 | J10: =(D10*1000000)/F10 -> 31268.091 | K10: =J10/$J$2*100 -> 108.83217 | L10: =(D10-D9)/D9*100 -> 0.26076734 | M10: {=TREND($D$2:$D$26,$A$2:$A$26,A10)} -> 1959473.6 | N10: =(D10-M10)/M10*100 -> 2.7259061 | O10: =(E10-E9)/E9*100 -> 2.8128619 | P10: =(H10-H9)/H9*100 -> 2.2994507 | Q10: =B10-B9 -> -0.6 | R10: =AVERAGE($B$2:$B$26) -> 8.792 | S10: =B10-R10 -> -1.392
A11: 39814 | B11: 9.1 | C11: 1936988.9 | D11: 1958036.5 | E11: 93.286667 | F11: 64706436 | H11: =C11/D11*100 -> 98.925066 | I11: =H11/$H$2*100 -> 117.34392 | J11: =(D11*1000000)/F11 -> 30260.305 | K11: =J11/$J$2*100 -> 105.32446 | L11: =(D11-D10)/D10*100 -> -2.7249667 | M11: {=TREND($D$2:$D$26,$A$2:$A$26,A11)} -> 1982104.9 | N11: =(D11-M11)/M11*100 -> -1.214284 | O11: =(E11-E10)/E10*100 -> 0.087620478 | P11: =(H11-H10)/H10*100 -> 0.11236182 | Q11: =B11-B10 -> 1.7 | R11: =AVERAGE($B$2:$B$26) -> 8.792 | S11: =B11-R11 -> 0.308
A12: 40179 | B12: 9.3 | C12: 1993991.5 | D12: 1993991.5 | E12: 94.715 | F12: 65026211 | H12: =C12/D12*100 -> 100 | I12: =H12/$H$2*100 -> 118.619 | J12: =(D12*1000000)/F12 -> 30664.427 | K12: =J12/$J$2*100 -> 106.73105 | L12: =(D12-D11)/D11*100 -> 1.8362783 | M12: {=TREND($D$2:$D$26,$A$2:$A$26,A12)} -> 2004674.3 | N12: =(D12-M12)/M12*100 -> -0.53289661 | O12: =(E12-E11)/E11*100 -> 1.5311227 | P12: =(H12-H11)/H11*100 -> 1.0866144 | Q12: =B12-B11 -> 0.2 | R12: =AVERAGE($B$2:$B$26) -> 8.792 | S12: =B12-R12 -> 0.508
A13: 40544 | B13: 9.2 | C13: 2060977.1 | D13: 2043487.9 | E13: 96.715 | F13: 65340830 | H13: =C13/D13*100 -> 100.85585 | I13: =H13/$H$2*100 -> 119.6342 | J13: =(D13*1000000)/F13 -> 31274.287 | K13: =J13/$J$2*100 -> 108.85374 | L13: =(D13-D12)/D12*100 -> 2.4822774 | M13: {=TREND($D$2:$D$26,$A$2:$A$26,A13)} -> 2027243.8 | N13: =(D13-M13)/M13*100 -> 0.80128988 | O13: =(E13-E12)/E12*100 -> 2.111598 | P13: =(H13-H12)/H12*100 -> 0.85585043 | Q13: =B13-B12 -> -0.1 | R13: =AVERAGE($B$2:$B$26) -> 8.792 | S13: =B13-R13 -> 0.408
A14: 40909 | B14: 9.8 | C14: 2087960 | D14: 2048137.5 | E14: 98.605 | F14: 65657659 | H14: =C14/D14*100 -> 101.94433 | I14: =H14/$H$2*100 -> 120.92534 | J14: =(D14*1000000)/F14 -> 31194.19 | K14: =J14/$J$2*100 -> 108.57495 | L14: =(D14-D13)/D13*100 -> 0.22753254 | M14: {=TREND($D$2:$D$26,$A$2:$A$26,A14)} -> 2049813.3 | N14: =(D14-M14)/M14*100 -> -0.081751823 | O14: =(E14-E13)/E13*100 -> 1.9541953 | P14: =(H14-H13)/H13*100 -> 1.0792404 | Q14: =B14-B13 -> 0.6 | R14: =AVERAGE($B$2:$B$26) -> 8.792 | S14: =B14-R14 -> 1.008
... A26: 45292 | B26: 7.5 | C26: 2936861.9 | D26: 2360180.8 | E26: 119.82083 | F26: 68551653 | H26: =C26/D26*100 -> 124.43377 | I26: =H26/$H$2*100 -> 147.60209 | J26: =(D26*1000000)/F26 -> 34429.233 | K26: =J26/$J$2*100 -> 119.83488 | L26: =(D26-D25)/D25*100 -> 1.4263884 | M26: {=TREND($D$2:$D$26,$A$2:$A$26,A26)} -> 2320832.3 | N26: =(D26-M26)/M26*100 -> 1.6954491 | O26: =(E26-E25)/E25*100 -> 1.9990494 | P26: =(H26-H25)/H25*100 -> 2.0400277 | Q26: =B26-B25 -> 0.2 | R26: =AVERAGE($B$2:$B$26) -> 8.792 | S26: =B26-R26 -> -1.292
A27: Data Sources | B27: FRED `LRHUTTTTFRM156S` | C27: FRED `CPMNACSCAB1GQFR` | D27: FRED `CLVMNACSCAB1GQFR` | E27: FRED `FRACPIALLMINMEI` | F27: FRED `POPTOTFRA647NWDB` | H27: Excel formula | I27: Excel formula | J27: Excel formula | K27: Excel formula | L27: Excel formula | M27: Excel formula | N27: Excel formula | O27: Excel formula | P27: Excel formula | Q27: Excel formula | R27: Excel formula | S27: Excel formula
H28: Nominal GDP / Real GDP × 100 | I28: GDP Deflator / GDP Deflator in 2000 × 100 | J28: (Real GDP × 1,000,000) / Population → EUR/person | K28: Real GDP per Capita / 2000 value × 100 | L28: (Real GDP_t − Real GDP_t−1) / Real GDP_t−1 × 100 | M28: TREND(Real GDP 2000–2024, time 2000–2024) | N28: (Actual Real GDP − Potential GDP) / Potential GDP × 100 | O28: (CPI_t − CPI_t−1) / CPI_t−1 × 100 | P28: (Deflator_t − Deflator_t−1) / Deflator_t−1 × 100 | Q28: Unemployment_t − Unemployment_t−1 | R28: AVERAGE(Unemployment, 2000–2024) | S28: Actual unemployment − full-sample average
A29: sample period | B29: 2000–2024 | C29: 2000–2024 | D29: 2000–2024 | E29: 2000–2024 | F29: 2000–2024 | G29: valid | H29: 2000–2024 | I29: 2000–2024 | J29: 2000–2024 | K29: 2000–2024 | L29: 2001–2024 | M29: 2000–2024 | N29: 2000–2024 | O29: 2001–2024 | P29: 2001–2024 | Q29: 2001–2024 | R29: 2000–2024 | S29: 2000–2024
A30: type | B30: Monthly harmonized unemployment rate (%) | C30: Quarterly nominal GDP (million EUR) | D30: Quarterly real GDP (million chained EUR) | E30: Monthly CPI index (2015 = 100) | F30: Annual population (persons) | G30: inputs | H30: C, D | I30: H | J30: D, F | K30: J | L30: D | M30: A, D | N30: D, M | O30: E | P30: H | Q30: B | R30: B | S30: B, R
A31: Data processing | B31: Converted to annual using the annual average. | C31: Four quarterly values were summed to obtain each annual GDP value. | D31: Four quarterly values were summed to obtain each annual real GDP value. | E31: Converted to annual using the annual average. | F31: Already annual; no frequency conversion. | G31: purpose | H31: Implicit price index for domestic output. | I31: Re-bases each country's deflator so 2000 = 100 for comparison. | J31: Converts GDP from millions of EUR to EUR before dividing by persons. | K31: Measures cumulative real-GDP-per-capita growth since 2000. | L31: Year-over-year real output growth. | M31: Full-sample linear trend used as the homework proxy for potential GDP. | N31: Measures actual output relative to the linear-trend proxy. | O31: Annual CPI inflation. | P31: Annual inflation implied by the GDP deflator. | Q31: Percentage-point change in unemployment; used in Okun scatter plot. | R31: Simple benchmark for the 'normal' unemployment rate in Q9. | S31: Positive values mean unemployment is above its 2000–2024 average.

Sheet Japan
A1: Year | B1: Unemployment rate | C1: Nominal GDP | D1: Real GDP | E1: CPI( base = 2015) | F1: population(person) | G1: cpi inflation input | I1: GDP Deflator | J1: GDP Deflator Index (2000=100) | K1: Real GDP per Capita (Yen/person) | L1: Real GDP per Capita Index (2000=100) | M1: Real GDP Growth (%) | N1: Potential GDP (Linear Trend) | O1: Output Gap (%) | P1: CPI Inflation Rate (%) | Q1: GDP Deflator Inflation Rate (%) | R1: Change in Unemployment Rate (pp) | S1: Average Unemployment Rate (%) | T1: Unemployment Gap (pp)
A2: 36526 | B2: 4.7 | C2: 543737.3 | D2: 500719.1 | E2: =E3/(1+G3/100) -> 99.105126 | F2: 126843000 | G2: -0.67657868 | I2: =C2/D2*100 -> 108.59128 | J2: =I2/$I$2*100 -> 100 | K2: =(D2*1000000000)/F2 -> 3947550.1 | L2: =K2/$K$2*100 -> 100 | N2: {=TREND($D$2:$D$26,$A$2:$A$26,A2)} -> 502660.39 | O2: =(D2-N2)/N2*100 -> -0.38620322 | S2: =AVERAGE($B$2:$B$26) -> 3.816 | T2: =B2-S2 -> 0.884
A3: 36892 | B3: 5 | C3: 539711.5 | D3: 502075.6 | E3: =E4/(1+G4/100) -> 98.371693 | F3: 127149000 | G3: -0.7400555 | I3: =C3/D3*100 -> 107.49606 | J3: =I3/$I$2*100 -> 98.991428 | K3: =(D3*1000000000)/F3 -> 3948718.4 | L3: =K3/$K$2*100 -> 100.0296 | M3: =(D3-D2)/D2*100 -> 0.27091038 | N3: {=TREND($D$2:$D$26,$A$2:$A$26,A3)} -> 506252.46 | O3: =(D3-N3)/N3*100 -> -0.82505445 | P3: =(E3-E2)/E2*100 -> -0.7400555 | Q3: =(I3-I2)/I2*100 -> -1.0085724 | R3: =B3-B2 -> 0.3 | S3: =AVERAGE($B$2:$B$26) -> 3.816 | T3: =B3-S3 -> 1.184
A4: 37257 | B4: 5.4 | C4: 532463.2 | D4: 502338.3 | E4: =E5/(1+G5/100) -> 97.463237 | F4: 127445000 | G4: -0.92349403 | I4: =C4/D4*100 -> 105.99693 | J4: =I4/$I$2*100 -> 97.610905 | K4: =(D4*1000000000)/F4 -> 3941608.5 | L4: =K4/$K$2*100 -> 99.849487 | M4: =(D4-D3)/D3*100 -> 0.052322798 | N4: {=TREND($D$2:$D$26,$A$2:$A$26,A4)} -> 509834.71 | O4: =(D4-N4)/N4*100 -> -1.4703612 | P4: =(E4-E3)/E3*100 -> -0.92349403 | Q4: =(I4-I3)/I3*100 -> -1.3945884 | R4: =B4-B3 -> 0.4 | S4: =AVERAGE($B$2:$B$26) -> 3.816 | T4: =B4-S4 -> 1.584
A5: 37622 | B5: 5.2 | C5: 530387.4 | D5: 509455.1 | E5: =E6/(1+G6/100) -> 97.213203 | F5: 127718000 | G5: -0.25654182 | I5: =C5/D5*100 -> 104.10876 | J5: =I5/$I$2*100 -> 95.872117 | K5: =(D5*1000000000)/F5 -> 3988906 | L5: =K5/$K$2*100 -> 101.04763 | M5: =(D5-D4)/D4*100 -> 1.4167345 | N5: {=TREND($D$2:$D$26,$A$2:$A$26,A5)} -> 513416.97 | O5: =(D5-N5)/N5*100 -> -0.77166621 | P5: =(E5-E4)/E4*100 -> -0.25654182 | Q5: =(I5-I4)/I4*100 -> -1.7813461 | R5: =B5-B4 -> -0.2 | S5: =AVERAGE($B$2:$B$26) -> 3.816 | T5: =B5-S5 -> 1.384
A6: 37987 | B6: 4.7 | C6: 534603.7 | D6: 520164.7 | E6: =E7/(1+G7/100) -> 97.204868 | F6: 127761000 | G6: -0.0085733882 | I6: =C6/D6*100 -> 102.77585 | J6: =I6/$I$2*100 -> 94.64466 | K6: =(D6*1000000000)/F6 -> 4071388.8 | L6: =K6/$K$2*100 -> 103.1371 | M6: =(D6-D5)/D5*100 -> 2.1021676 | N6: {=TREND($D$2:$D$26,$A$2:$A$26,A6)} -> 516999.22 | O6: =(D6-N6)/N6*100 -> 0.61227971 | P6: =(E6-E5)/E5*100 -> -0.0085733882 | Q6: =(I6-I5)/I5*100 -> -1.2803062 | R6: =B6-B5 -> -0.5 | S6: =AVERAGE($B$2:$B$26) -> 3.816 | T6: =B6-S6 -> 0.884
A7: 38353 | B7: 4.4 | C7: 537485.5 | D7: 529762 | E7: =E8/(1+G8/100) -> 96.929831 | F7: 127773000 | G7: -0.28294607 | I7: =C7/D7*100 -> 101.45792 | J7: =I7/$I$2*100 -> 93.430997 | K7: =(D7*1000000000)/F7 -> 4146118.5 | L7: =K7/$K$2*100 -> 105.03017 | M7: =(D7-D6)/D6*100 -> 1.8450502 | N7: {=TREND($D$2:$D$26,$A$2:$A$26,A7)} -> 520591.29 | O7: =(D7-N7)/N7*100 -> 1.7615957 | P7: =(E7-E6)/E6*100 -> -0.28294607 | Q7: =(I7-I6)/I6*100 -> -1.282337 | R7: =B7-B6 -> -0.3 | S7: =AVERAGE($B$2:$B$26) -> 3.816 | T7: =B7-S7 -> 0.584
A8: 38718 | B8: 4.1 | C8: 540568.1 | D8: 537815.5 | E8: =E9/(1+G9/100) -> 97.17153 | F8: 127854000 | G8: 0.24935512 | I8: =C8/D8*100 -> 100.51181 | J8: =I8/$I$2*100 -> 92.559741 | K8: =(D8*1000000000)/F8 -> 4206481.6 | L8: =K8/$K$2*100 -> 106.5593 | M8: =(D8-D7)/D7*100 -> 1.520211 | N8: {=TREND($D$2:$D$26,$A$2:$A$26,A8)} -> 524173.54 | O8: =(D8-N8)/N8*100 -> 2.6025656 | P8: =(E8-E7)/E7*100 -> 0.24935512 | Q8: =(I8-I7)/I7*100 -> -0.93251236 | R8: =B8-B7 -> -0.3 | S8: =AVERAGE($B$2:$B$26) -> 3.816 | T8: =B8-S8 -> 0.284
A9: 39083 | B9: 3.8 | C9: 544628.1 | D9: 547072.8 | E9: =E10/(1+G10/100) -> 97.229872 | F9: 128001000 | G9: 0.060039454 | I9: =C9/D9*100 -> 99.553131 | J9: =I9/$I$2*100 -> 91.676907 | K9: =(D9*1000000000)/F9 -> 4273972.9 | L9: =K9/$K$2*100 -> 108.269 | M9: =(D9-D8)/D8*100 -> 1.721278 | N9: {=TREND($D$2:$D$26,$A$2:$A$26,A9)} -> 527755.79 | O9: =(D9-N9)/N9*100 -> 3.6602169 | P9: =(E9-E8)/E8*100 -> 0.060039454 | Q9: =(I9-I8)/I8*100 -> -0.95379879 | R9: =B9-B8 -> -0.3 | S9: =AVERAGE($B$2:$B$26) -> 3.816 | T9: =B9-S9 -> -0.016
A10: 39448 | B10: 4 | C10: 533458.9 | D10: 540731.3 | E10: =E11/(1+G11/100) -> 98.571721 | F10: 128063000 | G10: 1.3800789 | I10: =C10/D10*100 -> 98.655081 | J10: =I10/$I$2*100 -> 90.849907 | K10: =(D10*1000000000)/F10 -> 4222385.1 | L10: =K10/$K$2*100 -> 106.96217 | M10: =(D10-D9)/D9*100 -> -1.1591693 | N10: {=TREND($D$2:$D$26,$A$2:$A$26,A10)} -> 531338.05 | O10: =(D10-N10)/N10*100 -> 1.7678488 | P10: =(E10-E9)/E9*100 -> 1.3800789 | Q10: =(I10-I9)/I9*100 -> -0.90208127 | R10: =B10-B9 -> 0.2 | S10: =AVERAGE($B$2:$B$26) -> 3.816 | T10: =B10-S10 -> 0.184
A11: 39814 | B11: 5.1 | C11: 499514.1 | D11: 508634.2 | E11: =E12/(1+G12/100) -> 97.238206 | F11: 128047000 | G11: -1.3528367 | I11: =C11/D11*100 -> 98.206943 | J11: =I11/$I$2*100 -> 90.437224 | K11: =(D11*1000000000)/F11 -> 3972246.1 | L11: =K11/$K$2*100 -> 100.6256 | M11: =(D11-D10)/D10*100 -> -5.9358687 | N11: {=TREND($D$2:$D$26,$A$2:$A$26,A11)} -> 534930.11 | O11: =(D11-N11)/N11*100 -> -4.9157663 | P11: =(E11-E10)/E10*100 -> -1.3528367 | Q11: =(I11-I10)/I10*100 -> -0.45424666 | R11: =B11-B10 -> 1.1 | S11: =AVERAGE($B$2:$B$26) -> 3.816 | T11: =B11-S11 -> 1.284
A12: 40179 | B12: 5.1 | C12: 510315.6 | D12: 529650.2 | E12: =E13/(1+G13/100) -> 96.530076 | F12: 128070000 | G12: -0.72824321 | I12: =C12/D12*100 -> 96.349553 | J12: =I12/$I$2*100 -> 88.726783 | K12: =(D12*1000000000)/F12 -> 4135630.5 | L12: =K12/$K$2*100 -> 104.76448 | M12: =(D12-D11)/D11*100 -> 4.1318496 | N12: {=TREND($D$2:$D$26,$A$2:$A$26,A12)} -> 538512.37 | O12: =(D12-N12)/N12*100 -> -1.6456758 | P12: =(E12-E11)/E11*100 -> -0.72824321 | Q12: =(I12-I11)/I11*100 -> -1.8913024 | R12: =B12-B11 -> 0 | S12: =AVERAGE($B$2:$B$26) -> 3.816 | T12: =B12-S12 -> 1.284
A13: 40544 | B13: 4.6 | C13: 501412.3 | D13: 528667.5 | E13: =E14/(1+G14/100) -> 96.267074 | F13: 127833000 | G13: -0.27245562 | I13: =C13/D13*100 -> 94.844548 | J13: =I13/$I$2*100 -> 87.340848 | K13: =(D13*1000000000)/F13 -> 4135610.5 | L13: =K13/$K$2*100 -> 104.76398 | M13: =(D13-D12)/D12*100 -> -0.18553755 | N13: {=TREND($D$2:$D$26,$A$2:$A$26,A13)} -> 542094.62 | O13: =(D13-N13)/N13*100 -> -2.4768963 | P13: =(E13-E12)/E12*100 -> -0.27245562 | Q13: =(I13-I12)/I12*100 -> -1.5620261 | R13: =B13-B12 -> -0.5 | S13: =AVERAGE($B$2:$B$26) -> 3.816 | T13: =B13-S13 -> 0.784
A14: 40909 | B14: 4.3 | C14: 505530 | D14: 537424 | E14: =E15/(1+G15/100) -> 96.224654 | F14: 127629000 | G14: -0.04406451 | I14: =C14/D14*100 -> 94.065393 | J14: =I14/$I$2*100 -> 86.623337 | K14: =(D14*1000000000)/F14 -> 4210829.8 | L14: =K14/$K$2*100 -> 106.66945 | M14: =(D14-D13)/D13*100 -> 1.6563341 | N14: {=TREND($D$2:$D$26,$A$2:$A$26,A14)} -> 545676.87 | O14: =(D14-N14)/N14*100 -> -1.5124106 | P14: =(E14-E13)/E13*100 -> -0.04406451 | Q14: =(I14-I13)/I13*100 -> -0.82150681 | R14: =B14-B13 -> -0.3 | S14: =AVERAGE($B$2:$B$26) -> 3.816 | T14: =B14-S14 -> 0.484
... A16: 41640 | B16: 3.6 | C16: 528094.1 | D16: 552778.6 | E16: =E17/(1+G17/100) -> 99.210995 | F16: 127276000 | G16: 2.7592267 | I16: =C16/D16*100 -> 95.534469 | J16: =I16/$I$2*100 -> 87.976185 | K16: =(D16*1000000000)/F16 -> 4343148.7 | L16: =K16/$K$2*100 -> 110.02137 | M16: =(D16-D15)/D15*100 -> 0.81909567 | N16: {=TREND($D$2:$D$26,$A$2:$A$26,A16)} -> 552851.2 | O16: =(D16-N16)/N16*100 -> -0.01313121 | P16: =(E16-E15)/E15*100 -> 2.7592267 | Q16: =(I16-I15)/I15*100 -> 1.7453236 | R16: =B16-B15 -> -0.4 | S16: =AVERAGE($B$2:$B$26) -> 3.816 | T16: =B16-S16 -> -0.216
A17: 42005 | B17: 3.4 | C17: 548919.1 | D17: 563010.3 | E17: =100 -> 100 | F17: 127141000 | G17: 0.79527963 | I17: =C17/D17*100 -> 97.497168 | J17: =I17/$I$2*100 -> 89.783604 | K17: =(D17*1000000000)/F17 -> 4428235.6 | L17: =K17/$K$2*100 -> 112.1768 | M17: =(D17-D16)/D16*100 -> 1.8509581 | N17: {=TREND($D$2:$D$26,$A$2:$A$26,A17)} -> 556433.45 | O17: =(D17-N17)/N17*100 -> 1.1819653 | P17: =(E17-E16)/E16*100 -> 0.79527963 | Q17: =(I17-I16)/I16*100 -> 2.0544411 | R17: =B17-B16 -> -0.2 | S17: =AVERAGE($B$2:$B$26) -> 3.816 | T17: =B17-S17 -> -0.416
A18: 42370 | B18: 3.1 | C18: 555766.3 | D18: 566785.5 | E18: =E17*(1+G18/100) -> 99.872741 | F18: 127076000 | G18: -0.12725884 | I18: =C18/D18*100 -> 98.055843 | J18: =I18/$I$2*100 -> 90.298079 | K18: =(D18*1000000000)/F18 -> 4460208.9 | L18: =K18/$K$2*100 -> 112.98676 | M18: =(D18-D17)/D17*100 -> 0.67053835 | N18: {=TREND($D$2:$D$26,$A$2:$A$26,A18)} -> 560015.7 | O18: =(D18-N18)/N18*100 -> 1.2088584 | P18: =(E18-E17)/E17*100 -> -0.12725884 | Q18: =(I18-I17)/I17*100 -> 0.57301628 | R18: =B18-B17 -> -0.3 | S18: =AVERAGE($B$2:$B$26) -> 3.816 | T18: =B18-S18 -> -0.716
A19: 42736 | B19: 2.8 | C19: 565040.4 | D19: 575995.2 | E19: =E18*(1+G19/100) -> 100.35632 | F19: 126972000 | G19: 0.4841998 | I19: =C19/D19*100 -> 98.098109 | J19: =I19/$I$2*100 -> 90.337001 | K19: =(D19*1000000000)/F19 -> 4536395.4 | L19: =K19/$K$2*100 -> 114.91673 | M19: =(D19-D18)/D18*100 -> 1.6249004 | N19: {=TREND($D$2:$D$26,$A$2:$A$26,A19)} -> 563607.77 | O19: =(D19-N19)/N19*100 -> 2.1978812 | P19: =(E19-E18)/E18*100 -> 0.4841998 | Q19: =(I19-I18)/I18*100 -> 0.043104168 | R19: =B19-B18 -> -0.3 | S19: =AVERAGE($B$2:$B$26) -> 3.816 | T19: =B19-S19 -> -1.016
A20: 43101 | B20: 2.4 | C20: 569196.6 | D20: 580909.6 | E20: =E19*(1+G20/100) -> 101.34894 | F20: 126811000 | G20: 0.9890946 | I20: =C20/D20*100 -> 97.983679 | J20: =I20/$I$2*100 -> 90.231624 | K20: =(D20*1000000000)/F20 -> 4580908.6 | L20: =K20/$K$2*100 -> 116.04434 | M20: =(D20-D19)/D19*100 -> 0.85320155 | N20: {=TREND($D$2:$D$26,$A$2:$A$26,A20)} -> 567190.02 | O20: =(D20-N20)/N20*100 -> 2.4188676 | P20: =(E20-E19)/E19*100 -> 0.9890946 | Q20: =(I20-I19)/I19*100 -> -0.11664829 | R20: =B20-B19 -> -0.4 | S20: =AVERAGE($B$2:$B$26) -> 3.816 | T20: =B20-S20 -> -1.416
A21: 43466 | B21: 2.4 | C21: 571848.8 | D21: 579096.5 | E21: =E20*(1+G21/100) -> 101.82404 | F21: 126633000 | G21: 0.46877616 | I21: =C21/D21*100 -> 98.748447 | J21: =I21/$I$2*100 -> 90.935887 | K21: =(D21*1000000000)/F21 -> 4573029.9 | L21: =K21/$K$2*100 -> 115.84476 | M21: =(D21-D20)/D20*100 -> -0.31211397 | N21: {=TREND($D$2:$D$26,$A$2:$A$26,A21)} -> 570772.28 | O21: =(D21-N21)/N21*100 -> 1.4584139 | P21: =(E21-E20)/E20*100 -> 0.46877616 | Q21: =(I21-I20)/I20*100 -> 0.78050503 | R21: =B21-B20 -> 0 | S21: =AVERAGE($B$2:$B$26) -> 3.816 | T21: =B21-S21 -> -1.416
A22: 43831 | B22: 2.8 | C22: 553828.6 | D22: 554019.5 | E22: =E21*(1+G22/100) -> 101.79859 | F22: 126261000 | G22: -0.024995834 | I22: =C22/D22*100 -> 99.965543 | J22: =I22/$I$2*100 -> 92.056691 | K22: =(D22*1000000000)/F22 -> 4387891 | L22: =K22/$K$2*100 -> 111.15479 | M22: =(D22-D21)/D21*100 -> -4.3303664 | N22: {=TREND($D$2:$D$26,$A$2:$A$26,A22)} -> 574354.53 | O22: =(D22-N22)/N22*100 -> -3.5405015 | P22: =(E22-E21)/E21*100 -> -0.024995834 | Q22: =(I22-I21)/I21*100 -> 1.2325215 | R22: =B22-B21 -> 0.4 | S22: =AVERAGE($B$2:$B$26) -> 3.816 | T22: =B22-S22 -> -1.016
A23: 44197 | B23: 2.8 | C23: 573724.1 | D23: 574267.8 | E23: =E22*(1+G23/100) -> 101.56104 | F23: 125681593 | G23: -0.23335278 | I23: =C23/D23*100 -> 99.905323 | J23: =I23/$I$2*100 -> 92.001235 | K23: =(D23*1000000000)/F23 -> 4569227.6 | L23: =K23/$K$2*100 -> 115.74844 | M23: =(D23-D22)/D22*100 -> 3.6547992 | N23: {=TREND($D$2:$D$26,$A$2:$A$26,A23)} -> 577946.6 | O23: =(D23-N23)/N23*100 -> -0.63652918 | P23: =(E23-E22)/E22*100 -> -0.23335278 | Q23: =(I23-I22)/I22*100 -> -0.060240569 | R23: =B23-B22 -> 0 | S23: =AVERAGE($B$2:$B$26) -> 3.816 | T23: =B23-S23 -> -1.016
A24: 44562 | B24: 2.6 | C24: 584979.8 | D24: 581669.5 | E24: =E23*(1+G24/100) -> 104.09773 | F24: 125124989 | G24: 2.4977028 | I24: =C24/D24*100 -> 100.5691 | J24: =I24/$I$2*100 -> 92.6125 | K24: =(D24*1000000000)/F24 -> 4648707.7 | L24: =K24/$K$2*100 -> 117.76184 | M24: =(D24-D23)/D23*100 -> 1.2888934 | N24: {=TREND($D$2:$D$26,$A$2:$A$26,A24)} -> 581528.85 | O24: =(D24-N24)/N24*100 -> 0.02418587 | P24: =(E24-E23)/E23*100 -> 2.4977028 | Q24: =(I24-I23)/I23*100 -> 0.66440937 | R24: =B24-B23 -> -0.2 | S24: =AVERAGE($B$2:$B$26) -> 3.816 | T24: =B24-S24 -> -1.216
A25: 44927 | B25: 2.6 | C25: 616029.6 | D25: 585811.2 | E25: =E24*(1+G25/100) -> 107.49979 | F25: 124516650 | G25: 3.2681337 | I25: =C25/D25*100 -> 105.15839 | J25: =I25/$I$2*100 -> 96.838698 | K25: =(D25*1000000000)/F25 -> 4704681.7 | L25: =K25/$K$2*100 -> 119.17978 | M25: =(D25-D24)/D24*100 -> 0.71203665 | N25: {=TREND($D$2:$D$26,$A$2:$A$26,A25)} -> 585111.11 | O25: =(D25-N25)/N25*100 -> 0.11965153 | P25: =(E25-E24)/E24*100 -> 3.2681337 | Q25: =(I25-I24)/I24*100 -> 4.5633123 | R25: =B25-B24 -> 0 | S25: =AVERAGE($B$2:$B$26) -> 3.816 | T25: =B25-S25 -> -1.216
A26: 45292 | B26: 2.5 | C26: 634646.6 | D26: 584868.6 | E26: =E25*(1+G26/100) -> 110.44371 | F26: 123975371 | G26: 2.7385368 | I26: =C26/D26*100 -> 108.51097 | J26: =I26/$I$2*100 -> 99.926041 | K26: =(D26*1000000000)/F26 -> 4717619.3 | L26: =K26/$K$2*100 -> 119.50752 | M26: =(D26-D25)/D25*100 -> -0.16090508 | N26: {=TREND($D$2:$D$26,$A$2:$A$26,A26)} -> 588693.36 | O26: =(D26-N26)/N26*100 -> -0.6497031 | P26: =(E26-E25)/E25*100 -> 2.7385368 | Q26: =(I26-I25)/I25*100 -> 3.18813 | R26: =B26-B25 -> -0.1 | S26: =AVERAGE($B$2:$B$26) -> 3.816 | T26: =B26-S26 -> -1.316
A27: Data Sources | B27: FRED `LRHUTTTTJPM156S` | C27: FRED `JPNNGDP` | D27: FRED `JPNRGDPEXP` | E27: Reconstructed from FRED `FPCPITOTLZGJPN` | F27: FRED `POPTOTJPA647NWDB` | G27: FRED `FPCPITOTLZGJPN` | I27: Excel formula | J27: Excel formula | K27: Excel formula | L27: Excel formula | M27: Excel formula | N27: Excel formula | O27: Excel formula | P27: Excel formula | Q27: Excel formula | R27: Excel formula | S27: Excel formula | T27: Excel formula
I28: Nominal GDP / Real GDP × 100 | J28: GDP Deflator / GDP Deflator in 2000 × 100 | K28: (Real GDP × 1,000,000,000) / Population → Yen/person | L28: Real GDP per Capita / 2000 value × 100 | M28: (Real GDP_t − Real GDP_t−1) / Real GDP_t−1 × 100 | N28: TREND(Real GDP 2000–2024, time 2000–2024) | O28: (Actual Real GDP − Potential GDP) / Potential GDP × 100 | P28: (Reconstructed CPI_t − Reconstructed CPI_t−1) / prior CPI × 100 | Q28: (Deflator_t − Deflator_t−1) / Deflator_t−1 × 100 | R28: Unemployment_t − Unemployment_t−1 | S28: AVERAGE(Unemployment, 2000–2024) | T28: Actual unemployment − full-sample average
A29: sample period | B29: 2000–2024 | C29: 2000–2024 | D29: 2000–2024 | E29: 2000–2024 | F29: 2000–2024 | G29: 2000–2024 | H29: valid | I29: 2000–2024 | J29: 2000–2024 | K29: 2000–2024 | L29: 2000–2024 | M29: 2001–2024 | N29: 2000–2024 | O29: 2000–2024 | P29: 2001–2024 | Q29: 2001–2024 | R29: 2001–2024 | S29: 2000–2024 | T29: 2000–2024
A30: type | B30: Monthly harmonized unemployment rate (%) | C30: Quarterly nominal GDP | D30: Quarterly real GDP | E30: Reconstructed CPI index (2015 = 100) | F30: Annual population (persons) | G30: Annual CPI inflation rate (%) | H30: inputs | I30: C, D | J30: I | K30: D, F | L30: K | M30: D | N30: A, D | O30: D, N | P30: E | Q30: I | R30: B | S30: B | T30: B, S
A31: Data processing | B31: Converted to annual using the annual average. | C31: Quarterly observations were averaged to annual values. | D31: Quarterly observations were averaged to annual values. | E31: CPI was reconstructed from annual CPI inflation, setting 2015 = 100 and chaining forward/backward. | F31: Already annual; no frequency conversion. | G31: Already annual; used as the input for CPI reconstruction. | H31: purpose | I31: Implicit price index for domestic output. | J31: Re-bases the deflator so 2000 = 100 for comparison. | K31: Converts GDP from billions of yen to yen before dividing by persons. | L31: Measures cumulative real-GDP-per-capita growth since 2000. | M31: Year-over-year real output growth. | N31: Full-sample linear trend used as the homework proxy for potential GDP. | O31: Measures actual output relative to the linear-trend proxy. | P31: Annual CPI inflation calculated from the reconstructed CPI index. | Q31: Annual inflation implied by the GDP deflator. | R31: Percentage-point change in unemployment; used in Okun scatter plot. | S31: Simple benchmark for the 'normal' unemployment rate in Q9. | T31: Positive values mean unemployment is above its 2000–2024 average.

Sheet UK
A1: Year | B1: Unemployment rate | C1: Nominal GDP | D1: Real GDP | E1: CPI(base = 2015) | F1: Population(person) | H1: GDP Deflator | I1: GDP Deflator Index (2000=100) | J1: Real GDP per Capita (GBP/person) | K1: Real GDP per Capita Index (2000=100) | L1: Real GDP Growth (%) | M1: Potential GDP (Linear Trend) | N1: Output Gap (%) | O1: CPI Inflation Rate (%) | P1: GDP Deflator Inflation Rate (%) | Q1: Change in Unemployment Rate (pp) | R1: Average Unemployment Rate (%) | S1: Unemployment Gap (pp)
A2: 36526 | B2: 5.5 | C2: 1104759 | D2: 1940007 | E2: 73.416667 | F2: 58892514 | H2: =C2/D2*100 -> 56.946135 | I2: =H2/$H$2*100 -> 100 | J2: =(D2*1000000)/F2 -> 32941.487 | K2: =J2/$J$2*100 -> 100 | M2: {=TREND($D$2:$D$26,$A$2:$A$26,A2)} -> 1980595.7 | N2: =(D2-M2)/M2*100 -> -2.0493186 | R2: =AVERAGE($B$2:$B$26) -> 5.448 | S2: =B2-R2 -> 0.052
A3: 36892 | B3: 5.1 | C3: 1150542 | D3: 1986393 | E3: 74.541667 | F3: 59119673 | H3: =C3/D3*100 -> 57.921167 | I3: =H3/$H$2*100 -> 101.7122 | J3: =(D3*1000000)/F3 -> 33599.526 | K3: =J3/$J$2*100 -> 101.9976 | L3: =(D3-D2)/D2*100 -> 2.3910223 | M3: {=TREND($D$2:$D$26,$A$2:$A$26,A3)} -> 2012934.2 | N3: =(D3-M3)/M3*100 -> -1.3185308 | O3: =(E3-E2)/E2*100 -> 1.5323496 | P3: =(H3-H2)/H2*100 -> 1.7122004 | Q3: =B3-B2 -> -0.4 | R3: =AVERAGE($B$2:$B$26) -> 5.448 | S3: =B3-R3 -> -0.348
A4: 37257 | B4: 5.2 | C4: 1194646 | D4: 2020341 | E4: 75.675 | F4: 59370479 | H4: =C4/D4*100 -> 59.130909 | I4: =H4/$H$2*100 -> 103.83656 | J4: =(D4*1000000)/F4 -> 34029.387 | K4: =J4/$J$2*100 -> 103.30252 | L4: =(D4-D3)/D3*100 -> 1.7090274 | M4: {=TREND($D$2:$D$26,$A$2:$A$26,A4)} -> 2045184.2 | N4: =(D4-M4)/M4*100 -> -1.2147189 | O4: =(E4-E3)/E3*100 -> 1.5204025 | P4: =(H4-H3)/H3*100 -> 2.0886016 | Q4: =B4-B3 -> 0.1 | R4: =AVERAGE($B$2:$B$26) -> 5.448 | S4: =B4-R4 -> -0.248
A5: 37622 | B5: 5 | C5: 1262502 | D5: 2085366 | E5: 76.716667 | F5: 59647577 | H5: =C5/D5*100 -> 60.541027 | I5: =H5/$H$2*100 -> 106.31279 | J5: =(D5*1000000)/F5 -> 34961.454 | K5: =J5/$J$2*100 -> 106.13198 | L5: =(D5-D4)/D4*100 -> 3.2185161 | M5: {=TREND($D$2:$D$26,$A$2:$A$26,A5)} -> 2077434.3 | N5: =(D5-M5)/M5*100 -> 0.38180151 | O5: =(E5-E4)/E4*100 -> 1.3765004 | P5: =(H5-H4)/H4*100 -> 2.3847397 | Q5: =B5-B4 -> -0.2 | R5: =AVERAGE($B$2:$B$26) -> 5.448 | S5: =B5-R5 -> -0.448
A6: 37987 | B6: 4.8 | C6: 1327143 | D6: 2133872 | E6: 77.783333 | F6: 59987905 | H6: =C6/D6*100 -> 62.194124 | I6: =H6/$H$2*100 -> 109.21571 | J6: =(D6*1000000)/F6 -> 35571.704 | K6: =J6/$J$2*100 -> 107.98451 | L6: =(D6-D5)/D5*100 -> 2.3260186 | M6: {=TREND($D$2:$D$26,$A$2:$A$26,A6)} -> 2109684.4 | N6: =(D6-M6)/M6*100 -> 1.1465029 | O6: =(E6-E5)/E5*100 -> 1.3903976 | P6: =(H6-H5)/H5*100 -> 2.7305397 | Q6: =B6-B5 -> -0.2 | R6: =AVERAGE($B$2:$B$26) -> 5.448 | S6: =B6-R6 -> -0.648
A7: 38353 | B7: 4.8 | C7: 1403249 | D7: 2193421 | E7: 79.408333 | F7: 60401206 | H7: =C7/D7*100 -> 63.975361 | I7: =H7/$H$2*100 -> 112.34364 | J7: =(D7*1000000)/F7 -> 36314.192 | K7: =J7/$J$2*100 -> 110.23847 | L7: =(D7-D6)/D6*100 -> 2.7906547 | M7: {=TREND($D$2:$D$26,$A$2:$A$26,A7)} -> 2142022.8 | N7: =(D7-M7)/M7*100 -> 2.3995146 | O7: =(E7-E6)/E6*100 -> 2.0891365 | P7: =(H7-H6)/H6*100 -> 2.8639952 | Q7: =B7-B6 -> 0 | R7: =AVERAGE($B$2:$B$26) -> 5.448 | S7: =B7-R7 -> -0.648
A8: 38718 | B8: 5.4 | C8: 1478080 | D8: 2241453 | E8: 81.358333 | F8: 60846820 | H8: =C8/D8*100 -> 65.94294 | I8: =H8/$H$2*100 -> 115.7988 | J8: =(D8*1000000)/F8 -> 36837.636 | K8: =J8/$J$2*100 -> 111.82748 | L8: =(D8-D7)/D7*100 -> 2.1898213 | M8: {=TREND($D$2:$D$26,$A$2:$A$26,A8)} -> 2174272.9 | N8: =(D8-M8)/M8*100 -> 3.0897716 | O8: =(E8-E7)/E7*100 -> 2.4556617 | P8: =(H8-H7)/H7*100 -> 3.075526 | Q8: =B8-B7 -> 0.6 | R8: =AVERAGE($B$2:$B$26) -> 5.448 | S8: =B8-R8 -> -0.048
A9: 39083 | B9: 5.3 | C9: 1551729 | D9: 2307148 | E9: 83.3 | F9: 61322463 | H9: =C9/D9*100 -> 67.257454 | I9: =H9/$H$2*100 -> 118.10714 | J9: =(D9*1000000)/F9 -> 37623.212 | K9: =J9/$J$2*100 -> 114.21224 | L9: =(D9-D8)/D8*100 -> 2.9309113 | M9: {=TREND($D$2:$D$26,$A$2:$A$26,A9)} -> 2206523 | N9: =(D9-M9)/M9*100 -> 4.5603415 | O9: =(E9-E8)/E8*100 -> 2.3865615 | P9: =(H9-H8)/H8*100 -> 1.9934114 | Q9: =B9-B8 -> -0.1 | R9: =AVERAGE($B$2:$B$26) -> 5.448 | S9: =B9-R9 -> -0.148
A10: 39448 | B10: 5.7 | C10: 1602217 | D10: 2306008 | E10: 86.233333 | F10: 61806995 | H10: =C10/D10*100 -> 69.480115 | I10: =H10/$H$2*100 -> 122.01024 | J10: =(D10*1000000)/F10 -> 37309.822 | K10: =J10/$J$2*100 -> 113.26089 | L10: =(D10-D9)/D9*100 -> -0.049411655 | M10: {=TREND($D$2:$D$26,$A$2:$A$26,A10)} -> 2238773.1 | N10: =(D10-M10)/M10*100 -> 3.003203 | O10: =(E10-E9)/E9*100 -> 3.5214086 | P10: =(H10-H9)/H9*100 -> 3.3047055 | Q10: =B10-B9 -> 0.4 | R10: =AVERAGE($B$2:$B$26) -> 5.448 | S10: =B10-R10 -> 0.252
A11: 39814 | B11: 7.6 | C11: 1559405 | D11: 2200222 | E11: 87.925 | F11: 62276270 | H11: =C11/D11*100 -> 70.874894 | I11: =H11/$H$2*100 -> 124.45953 | J11: =(D11*1000000)/F11 -> 35330.022 | K11: =J11/$J$2*100 -> 107.25084 | L11: =(D11-D10)/D10*100 -> -4.5874082 | M11: {=TREND($D$2:$D$26,$A$2:$A$26,A11)} -> 2271111.5 | N11: =(D11-M11)/M11*100 -> -3.1213588 | O11: =(E11-E10)/E10*100 -> 1.9617317 | P11: =(H11-H10)/H10*100 -> 2.0074506 | Q11: =B11-B10 -> 1.9 | R11: =AVERAGE($B$2:$B$26) -> 5.448 | S11: =B11-R11 -> 2.152
A12: 40179 | B12: 7.9 | C12: 1615839 | D12: 2249959 | E12: 90.116667 | F12: 62766365 | H12: =C12/D12*100 -> 71.816375 | I12: =H12/$H$2*100 -> 126.11282 | J12: =(D12*1000000)/F12 -> 35846.572 | K12: =J12/$J$2*100 -> 108.81892 | L12: =(D12-D11)/D11*100 -> 2.2605446 | M12: {=TREND($D$2:$D$26,$A$2:$A$26,A12)} -> 2303361.6 | N12: =(D12-M12)/M12*100 -> -2.3184646 | O12: =(E12-E11)/E11*100 -> 2.4926547 | P12: =(H12-H11)/H11*100 -> 1.3283714 | Q12: =B12-B11 -> 0.3 | R12: =AVERAGE($B$2:$B$26) -> 5.448 | S12: =B12-R12 -> 2.452
A13: 40544 | B13: 8.1 | C13: 1669945 | D13: 2269116 | E13: 93.591667 | F13: 63258810 | H13: =C13/D13*100 -> 73.594519 | I13: =H13/$H$2*100 -> 129.23532 | J13: =(D13*1000000)/F13 -> 35870.355 | K13: =J13/$J$2*100 -> 108.89112 | L13: =(D13-D12)/D12*100 -> 0.85143774 | M13: {=TREND($D$2:$D$26,$A$2:$A$26,A13)} -> 2335611.7 | N13: =(D13-M13)/M13*100 -> -2.8470361 | O13: =(E13-E12)/E12*100 -> 3.8561124 | P13: =(H13-H12)/H12*100 -> 2.4759582 | Q13: =B13-B12 -> 0.2 | R13: =AVERAGE($B$2:$B$26) -> 5.448 | S13: =B13-R13 -> 2.652
A14: 40909 | B14: 8 | C14: 1721708 | D14: 2303794 | E14: 96 | F14: 63711000 | H14: =C14/D14*100 -> 74.733592 | I14: =H14/$H$2*100 -> 131.23558 | J14: =(D14*1000000)/F14 -> 36160.067 | K14: =J14/$J$2*100 -> 109.77059 | L14: =(D14-D13)/D13*100 -> 1.5282603 | M14: {=TREND($D$2:$D$26,$A$2:$A$26,A14)} -> 2367861.8 | N14: =(D14-M14)/M14*100 -> -2.7057234 | O14: =(E14-E13)/E13*100 -> 2.5732348 | P14: =(H14-H13)/H13*100 -> 1.5477686 | Q14: =B14-B13 -> -0.1 | R14: =AVERAGE($B$2:$B$26) -> 5.448 | S14: =B14-R14 -> 2.552
... A26: 45292 | B26: 4.3 | C26: 2890254 | D26: 2780853 | E26: 132.84167 | F26: 69281000 | H26: =C26/D26*100 -> 103.93408 | I26: =H26/$H$2*100 -> 182.51297 | J26: =(D26*1000000)/F26 -> 40138.754 | K26: =J26/$J$2*100 -> 121.84864 | L26: =(D26-D25)/D25*100 -> 1.0424161 | M26: {=TREND($D$2:$D$26,$A$2:$A$26,A26)} -> 2755127.9 | N26: =(D26-M26)/M26*100 -> 0.9337183 | O26: =(E26-E25)/E25*100 -> 3.2715729 | P26: =(H26-H25)/H25*100 -> 3.9340807 | Q26: =B26-B25 -> 0.2 | R26: =AVERAGE($B$2:$B$26) -> 5.448 | S26: =B26-R26 -> -1.148
A27: Data Sources | B27: FRED `LRHUTTTTGBM156S` | C27: FRED `NGDPXDCGBA` | D27: FRED `NGDPRXDCGBA` | E27: FRED `GBRCPIALLMINMEI` | F27: FRED `POPTOTGBA647NWDB` | H27: Excel formula | I27: Excel formula | J27: Excel formula | K27: Excel formula | L27: Excel formula | M27: Excel formula | N27: Excel formula | O27: Excel formula | P27: Excel formula | Q27: Excel formula | R27: Excel formula | S27: Excel formula
H28: Nominal GDP / Real GDP × 100 | I28: GDP Deflator / GDP Deflator in 2000 × 100 | J28: (Real GDP × 1,000,000) / Population → GBP/person | K28: Real GDP per Capita / 2000 value × 100 | L28: (Real GDP_t − Real GDP_t−1) / Real GDP_t−1 × 100 | M28: TREND(Real GDP 2000–2024, time 2000–2024) | N28: (Actual Real GDP − Potential GDP) / Potential GDP × 100 | O28: (CPI_t − CPI_t−1) / CPI_t−1 × 100 | P28: (Deflator_t − Deflator_t−1) / Deflator_t−1 × 100 | Q28: Unemployment_t − Unemployment_t−1 | R28: AVERAGE(Unemployment, 2000–2024) | S28: Actual unemployment − full-sample average
A29: sample period | B29: 2000–2024 | C29: 2000–2024 | D29: 2000–2024 | E29: 2000–2024 | F29: 2000–2024 | G29: valid | H29: 2000–2024 | I29: 2000–2024 | J29: 2000–2024 | K29: 2000–2024 | L29: 2001–2024 | M29: 2000–2024 | N29: 2000–2024 | O29: 2001–2024 | P29: 2001–2024 | Q29: 2001–2024 | R29: 2000–2024 | S29: 2000–2024
A30: type | B30: Monthly harmonized unemployment rate (%) | C30: Annual nominal GDP (million domestic currency) | D30: Annual real GDP (million domestic currency) | E30: Monthly CPI index (2015 = 100) | F30: Annual population (persons) | G30: inputs | H30: C, D | I30: H | J30: D, F | K30: J | L30: D | M30: A, D | N30: D, M | O30: E | P30: H | Q30: B | R30: B | S30: B, R
A31: Data processing | B31: Converted to annual using the annual average. | C31: Already annual; no frequency conversion. | D31: Already annual; no frequency conversion. | E31: Converted to annual using the annual average. | F31: Already annual; no frequency conversion. | G31: purpose | H31: Implicit price index for domestic output. | I31: Re-bases each country's deflator so 2000 = 100 for comparison. | J31: Converts GDP from millions of GBP to GBP before dividing by persons. | K31: Measures cumulative real-GDP-per-capita growth since 2000. | L31: Year-over-year real output growth. | M31: Full-sample linear trend used as the homework proxy for potential GDP. | N31: Measures actual output relative to the linear-trend proxy. | O31: Annual CPI inflation. | P31: Annual inflation implied by the GDP deflator. | Q31: Percentage-point change in unemployment; used in Okun scatter plot. | R31: Simple benchmark for the 'normal' unemployment rate in Q9. | S31: Positive values mean unemployment is above its 2000–2024 average.

Sheet Iran
A1: Year | B1: Unemployment rate (%) | C1: Nominal GDP (Billion Rials) | D1: Real GDP - Linked CBI Series (Billion Rials, 2021/22 prices) | E1: CPI - Urban Households (1400=100) | F1: Population (persons) | H1: GDP Deflator | I1: GDP Deflator Index (2000=100) | J1: Real GDP per Capita (Rials/person) | K1: Real GDP per Capita Index (2000=100) | L1: Real GDP Growth (%) | M1: Potential GDP (Linear Trend) | N1: Output Gap (%) | O1: CPI Inflation Rate (%) | P1: GDP Deflator Inflation Rate (%) | Q1: Change in Unemployment Rate (pp) | R1: Average Unemployment Rate (%) | S1: Unemployment Gap (pp) | U1: Year | V1: CBI Real GDP Vintage: 2004/05 prices | W1: CBI Real GDP Vintage: 2016/17 prices | X1: CBI Real GDP Vintage: 2021/22 prices
A2: 2000 | C2: 628070.08 | D2: =$X$18*($W$13/$W$18)*(V2/$V$13) -> 36661890 | E2: 2.53 | F2: 64219319 | H2: =C2/D2*100 -> 1.7131416 | I2: =H2/$H$2*100 -> 100 | J2: =(D2*1000000000)/F2 -> 5.7088569e+08 | K2: =J2/$J$2*100 -> 100 | M2: {=TREND($D$2:$D$26,$A$2:$A$26,A2)} -> 40074526 | N2: =(D2-M2)/M2*100 -> -8.5157233 | R2: =AVERAGE($B$2:$B$26) -> 10.83565 | U2: 2000 | V2: 1261466
A3: 2001 | C3: 738307.45 | D3: =$X$18*($W$13/$W$18)*(V3/$V$13) -> 37538906 | E3: 2.822 | F3: 65301307 | H3: =C3/D3*100 -> 1.9667794 | I3: =H3/$H$2*100 -> 114.80542 | J3: =(D3*1000000000)/F3 -> 5.7485688e+08 | K3: =J3/$J$2*100 -> 100.69562 | L3: =(D3-D2)/D2*100 -> 2.3921727 | M3: {=TREND($D$2:$D$26,$A$2:$A$26,A3)} -> 41673279 | N3: =(D3-M3)/M3*100 -> -9.9209222 | O3: =(E3-E2)/E2*100 -> 11.541502 | P3: =(H3-H2)/H2*100 -> 14.805419 | R3: =AVERAGE($B$2:$B$26) -> 10.83565 | U3: 2001 | V3: 1291642.4
A4: 2002 | C4: 1023613 | D4: =$X$18*($W$13/$W$18)*(V4/$V$13) -> 40571610 | E4: 3.195 | F4: 66300418 | H4: =C4/D4*100 -> 2.5229785 | I4: =H4/$H$2*100 -> 147.27204 | J4: =(D4*1000000000)/F4 -> 6.1193596e+08 | K4: =J4/$J$2*100 -> 107.19063 | L4: =(D4-D3)/D3*100 -> 8.0788293 | M4: {=TREND($D$2:$D$26,$A$2:$A$26,A4)} -> 43272033 | N4: =(D4-M4)/M4*100 -> -6.2405738 | O4: =(E4-E3)/E3*100 -> 13.217576 | P4: =(H4-H3)/H3*100 -> 28.279694 | R4: =AVERAGE($B$2:$B$26) -> 10.83565 | U4: 2002 | V4: 1395992
A5: 2003 | C5: 1258128.7 | D5: =$X$18*($W$13/$W$18)*(V5/$V$13) -> 44076712 | E5: 3.639 | F5: 67314814 | H5: =C5/D5*100 -> 2.854407 | I5: =H5/$H$2*100 -> 166.61828 | J5: =(D5*1000000000)/F5 -> 6.5478473e+08 | K5: =J5/$J$2*100 -> 114.69629 | L5: =(D5-D4)/D4*100 -> 8.6392984 | M5: {=TREND($D$2:$D$26,$A$2:$A$26,A5)} -> 44870787 | N5: =(D5-M5)/M5*100 -> -1.7696911 | O5: =(E5-E4)/E4*100 -> 13.896714 | P5: =(H5-H4)/H4*100 -> 13.136394 | R5: =AVERAGE($B$2:$B$26) -> 10.83565 | U5: 2003 | V5: 1516595.9
A6: 2004 | C6: 1582365.6 | D6: =$X$18*($W$13/$W$18)*(V6/$V$13) -> 45988172 | E6: 4.171 | F6: 68344730 | H6: =C6/D6*100 -> 3.4408099 | I6: =H6/$H$2*100 -> 200.84796 | J6: =(D6*1000000000)/F6 -> 6.7288541e+08 | K6: =J6/$J$2*100 -> 117.86693 | L6: =(D6-D5)/D5*100 -> 4.336666 | M6: {=TREND($D$2:$D$26,$A$2:$A$26,A6)} -> 46469540 | N6: =(D6-M6)/M6*100 -> -1.0358789 | O6: =(E6-E5)/E5*100 -> 14.619401 | P6: =(H6-H5)/H5*100 -> 20.543776 | R6: =AVERAGE($B$2:$B$26) -> 10.83565 | U6: 2004 | V6: 1582365.6
A7: 2005 | B7: 11.575 | C7: 1970690.3 | D7: =$X$18*($W$13/$W$18)*(V7/$V$13) -> 47923672 | E7: 4.676 | F7: 69390405 | H7: =C7/D7*100 -> 4.1121437 | I7: =H7/$H$2*100 -> 240.03525 | J7: =(D7*1000000000)/F7 -> 6.9063831e+08 | K7: =J7/$J$2*100 -> 120.97664 | L7: =(D7-D6)/D6*100 -> 4.2086904 | M7: {=TREND($D$2:$D$26,$A$2:$A$26,A7)} -> 48068294 | N7: =(D7-M7)/M7*100 -> -0.30086785 | O7: =(E7-E6)/E6*100 -> 12.107408 | P7: =(H7-H6)/H6*100 -> 19.510923 | R7: =AVERAGE($B$2:$B$26) -> 10.83565 | S7: =B7-R7 -> 0.73935 | U7: 2005 | V7: 1648962.5
A8: 2006 | B8: 11.35 | C8: 2372025.4 | D8: =$X$18*($W$13/$W$18)*(V8/$V$13) -> 50657359 | E8: 5.316 | F8: 70495782 | H8: =C8/D8*100 -> 4.6824892 | I8: =H8/$H$2*100 -> 273.32763 | J8: =(D8*1000000000)/F8 -> 7.1858709e+08 | K8: =J8/$J$2*100 -> 125.87233 | L8: =(D8-D7)/D7*100 -> 5.7042519 | M8: {=TREND($D$2:$D$26,$A$2:$A$26,A8)} -> 49667047 | N8: =(D8-M8)/M8*100 -> 1.9939001 | O8: =(E8-E7)/E7*100 -> 13.686912 | P8: =(H8-H7)/H7*100 -> 13.869785 | Q8: =B8-B7 -> -0.225 | R8: =AVERAGE($B$2:$B$26) -> 10.83565 | S8: =B8-R8 -> 0.51435 | U8: 2006 | V8: 1743023.5
A9: 2007 | B9: 10.6 | C9: 3132151.9 | D9: =$X$18*($W$13/$W$18)*(V9/$V$13) -> 55275368 | E9: 6.232 | F9: 71366189 | H9: =C9/D9*100 -> 5.6664515 | I9: =H9/$H$2*100 -> 330.76376 | J9: =(D9*1000000000)/F9 -> 7.745316e+08 | K9: =J9/$J$2*100 -> 135.67192 | L9: =(D9-D8)/D8*100 -> 9.1161674 | M9: {=TREND($D$2:$D$26,$A$2:$A$26,A9)} -> 51265801 | N9: =(D9-M9)/M9*100 -> 7.8211346 | O9: =(E9-E8)/E8*100 -> 17.231001 | P9: =(H9-H8)/H8*100 -> 21.013658 | Q9: =B9-B8 -> -0.75 | R9: =AVERAGE($B$2:$B$26) -> 10.83565 | S9: =B9-R9 -> -0.23565 | U9: 2007 | V9: 1901920.4
A10: 2008 | B10: 10.475 | C10: 3744913.1 | D10: =$X$18*($W$13/$W$18)*(V10/$V$13) -> 55785945 | E10: 7.824 | F10: 72266219 | H10: =C10/D10*100 -> 6.7130047 | I10: =H10/$H$2*100 -> 391.85347 | J10: =(D10*1000000000)/F10 -> 7.7195051e+08 | K10: =J10/$J$2*100 -> 135.2198 | L10: =(D10-D9)/D9*100 -> 0.92369579 | M10: {=TREND($D$2:$D$26,$A$2:$A$26,A10)} -> 52864555 | N10: =(D10-M10)/M10*100 -> 5.526179 | O10: =(E10-E9)/E9*100 -> 25.545571 | P10: =(H10-H9)/H9*100 -> 18.469287 | Q10: =B10-B9 -> -0.125 | R10: =AVERAGE($B$2:$B$26) -> 10.83565 | S10: =B10-R10 -> -0.36065 | U10: 2008 | V10: 1919488.3
A11: 2009 | B11: 12.025 | C11: 3935640.7 | D11: =$X$18*($W$13/$W$18)*(V11/$V$13) -> 57077228 | E11: 8.565 | F11: 73196424 | H11: =C11/D11*100 -> 6.8952906 | I11: =H11/$H$2*100 -> 402.49391 | J11: =(D11*1000000000)/F11 -> 7.7978164e+08 | K11: =J11/$J$2*100 -> 136.59156 | L11: =(D11-D10)/D10*100 -> 2.3147106 | M11: {=TREND($D$2:$D$26,$A$2:$A$26,A11)} -> 54463308 | N11: =(D11-M11)/M11*100 -> 4.7994137 | O11: =(E11-E10)/E10*100 -> 9.4708589 | P11: =(H11-H10)/H10*100 -> 2.7154148 | Q11: =B11-B10 -> 1.55 | R11: =AVERAGE($B$2:$B$26) -> 10.83565 | S11: =B11-R11 -> 1.18935 | U11: 2009 | V11: 1963918.9
A12: 2010 | B12: 13.525 | C12: 4796803.4 | D12: =$X$18*($W$13/$W$18)*(V12/$V$13) -> 60831411 | E12: 9.758 | F12: 74157377 | H12: =C12/D12*100 -> 7.8854056 | I12: =H12/$H$2*100 -> 460.28919 | J12: =(D12*1000000000)/F12 -> 8.2030154e+08 | K12: =J12/$J$2*100 -> 143.68928 | L12: =(D12-D11)/D11*100 -> 6.5773744 | M12: {=TREND($D$2:$D$26,$A$2:$A$26,A12)} -> 56062062 | N12: =(D12-M12)/M12*100 -> 8.5072661 | O12: =(E12-E11)/E11*100 -> 13.92878 | P12: =(H12-H11)/H11*100 -> 14.359293 | Q12: =B12-B11 -> 1.5 | R12: =AVERAGE($B$2:$B$26) -> 10.83565 | S12: =B12-R12 -> 2.68935 | U12: 2010 | V12: 2093093.2
A13: 2011 | B13: 12.325 | C13: 6895999.7 | D13: =$X$18*(W13/$W$18) -> 63112400 | E13: 12.33 | F13: 75149669 | H13: =C13/D13*100 -> 10.926537 | I13: =H13/$H$2*100 -> 637.807 | J13: =(D13*1000000000)/F13 -> 8.3982273e+08 | K13: =J13/$J$2*100 -> 147.10874 | L13: =(D13-D12)/D12*100 -> 3.7496905 | M13: {=TREND($D$2:$D$26,$A$2:$A$26,A13)} -> 57660816 | N13: =(D13-M13)/M13*100 -> 9.4545745 | O13: =(E13-E12)/E12*100 -> 26.35786 | P13: =(H13-H12)/H12*100 -> 38.566581 | Q13: =B13-B12 -> -1.2 | R13: =AVERAGE($B$2:$B$26) -> 10.83565 | S13: =B13-R13 -> 1.48935 | U13: 2011 | V13: 2171577.8 | W13: 13498795
A14: 2012 | B14: 12.15 | C14: 7895676.8 | D14: =$X$18*(W14/$W$18) -> 60747471 | E14: 15.851 | F14: 76075000 | H14: =C14/D14*100 -> 12.99754 | I14: =H14/$H$2*100 -> 758.6962 | J14: =(D14*1000000000)/F14 -> 7.9852081e+08 | K14: =J14/$J$2*100 -> 139.87403 | L14: =(D14-D13)/D13*100 -> -3.7471714 | M14: {=TREND($D$2:$D$26,$A$2:$A$26,A14)} -> 59259569 | N14: =(D14-M14)/M14*100 -> 2.5108204 | O14: =(E14-E13)/E13*100 -> 28.556367 | P14: =(H14-H13)/H13*100 -> 18.953884 | Q14: =B14-B13 -> -0.175 | R14: =AVERAGE($B$2:$B$26) -> 10.83565 | S14: =B14-R14 -> 1.31435 | U14: 2012 | W14: 12992972
A15: 2013 | B15: 10.45 | C15: 10634998 | D15: =$X$18*(W15/$W$18) -> 59822907 | E15: 20.935 | F15: 77016000 | H15: =C15/D15*100 -> 17.777468 | I15: =H15/$H$2*100 -> 1037.7115 | J15: =(D15*1000000000)/F15 -> 7.7675946e+08 | K15: =J15/$J$2*100 -> 136.06217 | L15: =(D15-D14)/D14*100 -> -1.5219792 | M15: {=TREND($D$2:$D$26,$A$2:$A$26,A15)} -> 60858323 | N15: =(D15-M15)/M15*100 -> -1.7013551 | O15: =(E15-E14)/E14*100 -> 32.073686 | P15: =(H15-H14)/H14*100 -> 36.775632 | Q15: =B15-B14 -> -1.7 | R15: =AVERAGE($B$2:$B$26) -> 10.83565 | S15: =B15-R15 -> -0.38565 | U15: 2013 | W15: 12795222
A16: 2014 | B16: 10.55 | C16: 12254708 | D16: =$X$18*(W16/$W$18) -> 62804944 | E16: 24.039 | F16: 77970000 | H16: =C16/D16*100 -> 19.512329 | I16: =H16/$H$2*100 -> 1138.9794 | J16: =(D16*1000000000)/F16 -> 8.055014e+08 | K16: =J16/$J$2*100 -> 141.09679 | L16: =(D16-D15)/D15*100 -> 4.9847751 | M16: {=TREND($D$2:$D$26,$A$2:$A$26,A16)} -> 62457076 | N16: =(D16-M16)/M16*100 -> 0.5569706 | O16: =(E16-E15)/E15*100 -> 14.826845 | P16: =(H16-H15)/H15*100 -> 9.7587687 | Q16: =B16-B15 -> 0.1 | R16: =AVERAGE($B$2:$B$26) -> 10.83565 | S16: =B16-R16 -> -0.28565 | U16: 2014 | W16: 13433035
A17: 2015 | B17: 11.05 | C17: 12103890 | D17: =$X$18*(W17/$W$18) -> 61910046 | E17: 26.752 | F17: 78940000 | H17: =C17/D17*100 -> 19.550769 | I17: =H17/$H$2*100 -> 1141.2232 | J17: =(D17*1000000000)/F17 -> 7.8426711e+08 | K17: =J17/$J$2*100 -> 137.37726 | L17: =(D17-D16)/D16*100 -> -1.4248849 | M17: {=TREND($D$2:$D$26,$A$2:$A$26,A17)} -> 64055830 | N17: =(D17-M17)/M17*100 -> -3.3498657 | O17: =(E17-E16)/E16*100 -> 11.285827 | P17: =(H17-H16)/H16*100 -> 0.19700167 | Q17: =B17-B16 -> 0.5 | R17: =AVERAGE($B$2:$B$26) -> 10.83565 | S17: =B17-R17 -> 0.21435 | U17: 2015 | W17: 13241630
A18: 2016 | B18: 12.425 | C18: 15023342 | D18: =X18 -> 67367470 | E18: 28.558 | F18: 79877000 | H18: =C18/D18*100 -> 22.300589 | I18: =H18/$H$2*100 -> 1301.7365 | J18: =(D18*1000000000)/F18 -> 8.4339009e+08 | K18: =J18/$J$2*100 -> 147.73362 | L18: =(D18-D17)/D17*100 -> 8.8150866 | M18: {=TREND($D$2:$D$26,$A$2:$A$26,A18)} -> 65654584 | N18: =(D18-M18)/M18*100 -> 2.6089363 | O18: =(E18-E17)/E17*100 -> 6.7508971 | P18: =(H18-H17)/H17*100 -> 14.065021 | Q18: =B18-B17 -> 1.375 | R18: =AVERAGE($B$2:$B$26) -> 10.83565 | S18: =B18-R18 -> 1.58935 | U18: 2016 | W18: 14408891 | X18: 67367470
A19: 2017 | B19: 12.1 | C19: 17457348 | D19: =X19 -> 69406585 | E19: 30.88 | F19: 81053000 | H19: =C19/D19*100 -> 25.152293 | I19: =H19/$H$2*100 -> 1468.197 | J19: =(D19*1000000000)/F19 -> 8.5631112e+08 | K19: =J19/$J$2*100 -> 149.99695 | L19: =(D19-D18)/D18*100 -> 3.0268547 | M19: {=TREND($D$2:$D$26,$A$2:$A$26,A19)} -> 67253337 | N19: =(D19-M19)/M19*100 -> 3.201697 | O19: =(E19-E18)/E18*100 -> 8.1308215 | P19: =(H19-H18)/H18*100 -> 12.787574 | Q19: =B19-B18 -> -0.325 | R19: =AVERAGE($B$2:$B$26) -> 10.83565 | S19: =B19-R19 -> 1.26435 | U19: 2017 | X19: 69406585
A20: 2018 | B20: 12.05 | C20: 22333174 | D20: =X20 -> 66805254 | E20: 39.104 | F20: 81962000 | H20: =C20/D20*100 -> 33.430266 | I20: =H20/$H$2*100 -> 1951.4012 | J20: =(D20*1000000000)/F20 -> 8.1507594e+08 | K20: =J20/$J$2*100 -> 142.77393 | L20: =(D20-D19)/D19*100 -> -3.7479602 | M20: {=TREND($D$2:$D$26,$A$2:$A$26,A20)} -> 68852091 | N20: =(D20-M20)/M20*100 -> -2.9728025 | O20: =(E20-E19)/E19*100 -> 26.632124 | P20: =(H20-H19)/H19*100 -> 32.911403 | Q20: =B20-B19 -> -0.05 | R20: =AVERAGE($B$2:$B$26) -> 10.83565 | S20: =B20-R20 -> 1.21435 | U20: 2018 | X20: 66805254
A21: 2019 | B21: 10.65 | C21: 28551162 | D21: =X21 -> 65227691 | E21: 52.546 | F21: 82710000 | H21: =C21/D21*100 -> 43.771536 | I21: =H21/$H$2*100 -> 2555.0448 | J21: =(D21*1000000000)/F21 -> 7.8863126e+08 | K21: =J21/$J$2*100 -> 138.14171 | L21: =(D21-D20)/D20*100 -> -2.3614354 | M21: {=TREND($D$2:$D$26,$A$2:$A$26,A21)} -> 70450845 | N21: =(D21-M21)/M21*100 -> -7.4138973 | O21: =(E21-E20)/E20*100 -> 34.375 | P21: =(H21-H20)/H20*100 -> 30.933855 | Q21: =B21-B20 -> -1.4 | R21: =AVERAGE($B$2:$B$26) -> 10.83565 | S21: =B21-R21 -> -0.18565 | U21: 2019 | X21: 65227691
A22: 2020 | B22: 9.609 | C22: 43708246 | D22: =X22 -> 68124981 | E22: 71.568 | F22: 83409000 | H22: =C22/D22*100 -> 64.158912 | I22: =H22/$H$2*100 -> 3745.1027 | J22: =(D22*1000000000)/F22 -> 8.1675815e+08 | K22: =J22/$J$2*100 -> 143.0686 | L22: =(D22-D21)/D21*100 -> 4.4418087 | M22: {=TREND($D$2:$D$26,$A$2:$A$26,A22)} -> 72049598 | N22: =(D22-M22)/M22*100 -> -5.4471055 | O22: =(E22-E21)/E21*100 -> 36.200662 | P22: =(H22-H21)/H21*100 -> 46.57679 | Q22: =B22-B21 -> -1.041 | R22: =AVERAGE($B$2:$B$26) -> 10.83565 | S22: =B22-R22 -> -1.22665 | U22: 2020 | X22: 68124981
A23: 2021 | B23: 9.179 | C23: 70939153 | D23: =X23 -> 70939153 | E23: 100 | F23: 84055000 | H23: =C23/D23*100 -> 100 | I23: =H23/$H$2*100 -> 5837.2292 | J23: =(D23*1000000000)/F23 -> 8.4396114e+08 | K23: =J23/$J$2*100 -> 147.83365 | L23: =(D23-D22)/D22*100 -> 4.1308969 | M23: {=TREND($D$2:$D$26,$A$2:$A$26,A23)} -> 73648352 | N23: =(D23-M23)/M23*100 -> -3.6785597 | O23: =(E23-E22)/E22*100 -> 39.727252 | P23: =(H23-H22)/H22*100 -> 55.862992 | Q23: =B23-B22 -> -0.43 | R23: =AVERAGE($B$2:$B$26) -> 10.83565 | S23: =B23-R23 -> -1.65665 | U23: 2021 | X23: 70939153
A24: 2022 | B24: 9 | C24: 1.1183826e+08 | D24: =X24 -> 74027000 | E24: 144.958 | F24: 84700000 | H24: =C24/D24*100 -> 151.07766 | I24: =H24/$H$2*100 -> 8818.749 | J24: =(D24*1000000000)/F24 -> 8.7399056e+08 | K24: =J24/$J$2*100 -> 153.09379 | L24: =(D24-D23)/D23*100 -> 4.3528109 | M24: {=TREND($D$2:$D$26,$A$2:$A$26,A24)} -> 75247105 | N24: =(D24-M24)/M24*100 -> -1.6214644 | O24: =(E24-E23)/E23*100 -> 44.958 | P24: =(H24-H23)/H23*100 -> 51.077656 | Q24: =B24-B23 -> -0.179 | R24: =AVERAGE($B$2:$B$26) -> 10.83565 | S24: =B24-R24 -> -1.83565 | U24: 2022 | X24: 74027000
A25: 2023 | B25: 8.075 | C25: 1.6173459e+08 | D25: =X25 -> 77974380 | E25: 203.96 | F25: 85329000 | H25: =C25/D25*100 -> 207.42017 | I25: =H25/$H$2*100 -> 12107.59 | J25: =(D25*1000000000)/F25 -> 9.1380867e+08 | K25: =J25/$J$2*100 -> 160.06859 | L25: =(D25-D24)/D24*100 -> 5.3323512 | M25: {=TREND($D$2:$D$26,$A$2:$A$26,A25)} -> 76845859 | N25: =(D25-M25)/M25*100 -> 1.4685514 | O25: =(E25-E24)/E24*100 -> 40.702824 | P25: =(H25-H24)/H24*100 -> 37.293742 | Q25: =B25-B24 -> -0.925 | R25: =AVERAGE($B$2:$B$26) -> 10.83565 | S25: =B25-R25 -> -2.76065 | U25: 2023 | X25: 77974380
A26: 2024 | B26: 7.55 | C26: 2.1522504e+08 | D26: =X26 -> 80830676 | E26: 270.836 | F26: 85961000 | H26: =C26/D26*100 -> 266.26653 | I26: =H26/$H$2*100 -> 15542.588 | J26: =(D26*1000000000)/F26 -> 9.40318e+08 | K26: =J26/$J$2*100 -> 164.71213 | L26: =(D26-D25)/D25*100 -> 3.6631206 | M26: {=TREND($D$2:$D$26,$A$2:$A$26,A26)} -> 78444613 | N26: =(D26-M26)/M26*100 -> 3.0417167 | O26: =(E26-E25)/E25*100 -> 32.788782 | P26: =(H26-H25)/H25*100 -> 28.370611 | Q26: =B26-B25 -> -0.525 | R26: =AVERAGE($B$2:$B$26) -> 10.83565 | S26: =B26-R26 -> -3.28565 | U26: 2024 | X26: 80830676
A27: Data Sources | B27: SCI Labour Force Survey | C27: CBI Annual National Accounts | D27: CBI Annual National Accounts - linked real GDP | E27: SCI CPI - Urban Households | F27: SCI Population Estimates / Projections | H27: Excel formula | I27: Excel formula | J27: Excel formula | K27: Excel formula | L27: Excel formula | M27: Excel formula | N27: Excel formula | O27: Excel formula | P27: Excel formula | Q27: Excel formula | R27: Excel formula | S27: Excel formula
G28: definition | H28: Nominal GDP / Real GDP x 100 | I28: GDP Deflator / GDP Deflator in 2000 x 100 | J28: (Real GDP x 1,000,000,000) / Population | K28: Real GDP per Capita / 2000 value x 100 | L28: (Real GDP_t - Real GDP_t-1) / Real GDP_t-1 x 100 | M28: TREND(Real GDP 2000-2024, time 2000-2024) | N28: (Actual Real GDP - Potential GDP) / Potential GDP x 100 | O28: (CPI_t - CPI_t-1) / CPI_t-1 x 100 | P28: (Deflator_t - Deflator_t-1) / Deflator_t-1 x 100 | Q28: Unemployment_t - Unemployment_t-1 | R28: AVERAGE(available unemployment observations) | S28: Actual unemployment - available-sample average | U28: Supporting CBI constant-price GDP vintages used only to construct linked Real GDP in column D
A29: sample period | B29: 2005-2024 | C29: 2000-2024 | D29: 2000-2024 | E29: 2000-2024 | F29: 2000-2024 | G29: valid | H29: 2000-2024 | I29: 2000-2024 | J29: 2000-2024 | K29: 2000-2024 | L29: 2001-2024 | M29: 2000-2024 | N29: 2000-2024 | O29: 2001-2024 | P29: 2001-2024 | Q29: 2006-2024 | R29: 2005-2024 | S29: 2005-2024 | U29: Link rule | V29: 2000-2010: backcast from linked 2011 using 2004/05-vintage ratios | W29: 2011-2015: backcast from 2016 using 2016/17-vintage ratios | X29: 2016-2024: latest 2021/22-price levels used directly
A30: type | B30: Quarterly unemployment rate, population age 15+ (%) | C30: Annual nominal GDP at current prices (billion rials) | D30: Linked annual real GDP, expressed on latest 2021/22-price scale (billion rials) | E30: Annual CPI index for urban households (1400=100) | F30: Annual total population (persons) | G30: input | H30: C, D | I30: H | J30: D, F | K30: J | L30: D | M30: A, D | N30: D, M | O30: E | P30: H | Q30: B | R30: B | S30: B, R | U30: Overlap years | V30: 2011 | W30: 2016 | X30: Latest scale: 2021/22
A31: Data processing | B31: Quarterly rates were converted to annual values using the arithmetic average. Iranian years were mapped to workbook years by adding 621. | C31: Gross Domestic Expenditure at market prices was taken from the newest available CBI annual-account vintage for each segment. | D31: CBI constant-price vintages (2004/05, 2016/17, 2021/22) were linked through overlapping years; the final series is on the 2021/22-price scale. | E31: The SCI annual CPI series was used directly. Iranian years 1379-1403 were labeled 2000-2024 by adding 621. | F31: SCI figures reported in thousand persons were multiplied by 1,000. Historical estimates and later projections were combined. | G31: purpose | H31: Implicit price index based on current-price GDP and the linked real-GDP series. | I31: Re-bases Iran's deflator so 2000=100 for cross-country comparison. | J31: Converts real GDP from billion rials to rials before dividing by persons. | K31: Measures cumulative real-GDP-per-capita growth since 2000. | L31: Year-over-year growth of the linked real-GDP series. | M31: Full-sample linear trend used as the homework proxy for potential GDP. | N31: Measures actual real GDP relative to the linear-trend proxy. | O31: Annual CPI inflation. | P31: Annual inflation implied by the linked GDP deflator. | Q31: Percentage-point change in unemployment; first valid change is 2006. | R31: Simple benchmark for normal unemployment using the consistent 2005-2024 SCI sample. | S31: Positive values mean unemployment is above its 2005-2024 average. | U31: Purpose | V31: Preserve historical growth | W31: Bridge to latest vintage | X31: Avoid artificial jumps from base-year changes

Sheet Comaprison
B1: Q1 - GDP Deflator Index (2000=100)
A2: Year | B2: USA | C2: GERMANY | D2: CHINA | E2: ITALY | F2: FRANCE | G2: JAPAN | H2: UK | I2: IRAN
A3: 2000 | B3: =USA!I2 -> 100 | C3: =Germany!I2 -> 100 | D3: =China!J2 -> 100 | E3: =Italy!I2 -> 100 | F3: =France!I2 -> 100 | G3: =Japan!J2 -> 100 | H3: =UK!I2 -> 100 | I3: =Iran!I2 -> 100
A4: 2001 | B4: =USA!I3 -> 102.25169 | C4: =Germany!I3 -> 101.43654 | D4: =China!J3 -> 102.22398 | E4: =Italy!I3 -> 103.06392 | F4: =France!I3 -> 101.90569 | G4: =Japan!J3 -> 98.991428 | H4: =UK!I3 -> 101.7122 | I4: =Iran!I3 -> 114.80542
A5: 2002 | B5: =USA!I4 -> 103.84068 | C5: =Germany!I4 -> 102.95461 | D5: =China!J4 -> 102.92177 | E5: =Italy!I4 -> 106.47113 | F5: =France!I4 -> 104.00934 | G5: =Japan!J4 -> 97.610905 | H5: =UK!I4 -> 103.83656 | I5: =Iran!I4 -> 147.27204
A6: 2003 | B6: =USA!I5 -> 105.89081 | C6: =Germany!I5 -> 104.32174 | D6: =China!J5 -> 105.6592 | E6: =Italy!I5 -> 109.84366 | F6: =France!I5 -> 105.88094 | G6: =Japan!J5 -> 95.872117 | H6: =UK!I5 -> 106.31279 | I6: =Iran!I5 -> 166.61828
A7: 2004 | B7: =USA!I6 -> 108.73831 | C7: =Germany!I6 -> 105.5179 | D7: =China!J6 -> 113.07716 | E7: =Italy!I6 -> 112.73712 | F7: =France!I6 -> 107.60657 | G7: =Japan!J6 -> 94.64466 | H7: =UK!I6 -> 109.21571 | I7: =Iran!I6 -> 200.84796
A8: 2005 | B8: =USA!I7 -> 112.14775 | C8: =Germany!I7 -> 106.08248 | D8: =China!J7 -> 117.27224 | E8: =Italy!I7 -> 115.08341 | F8: =France!I7 -> 109.72603 | G8: =Japan!J7 -> 93.430997 | H8: =UK!I7 -> 112.34364 | I8: =Iran!I7 -> 240.03525
A9: 2006 | B9: =USA!I8 -> 115.60621 | C9: =Germany!I8 -> 106.55563 | D9: =China!J8 -> 121.95848 | E9: =Italy!I8 -> 117.62684 | F9: =France!I8 -> 111.90815 | G9: =Japan!J8 -> 92.559741 | H9: =UK!I8 -> 115.7988 | I9: =Iran!I8 -> 273.32763
A10: 2007 | B10: =USA!I9 -> 118.73826 | C10: =Germany!I9 -> 108.51441 | D10: =China!J9 -> 131.55227 | E10: =Italy!I9 -> 120.52878 | F10: =France!I9 -> 114.57756 | G10: =Japan!J9 -> 91.676907 | H10: =UK!I9 -> 118.10714 | I10: =Iran!I9 -> 330.76376
A11: 2008 | B11: =USA!I10 -> 121.02602 | C11: =Germany!I10 -> 109.55604 | D11: =China!J10 -> 141.84935 | E11: =Italy!I10 -> 123.42686 | F11: =France!I10 -> 117.21222 | G11: =Japan!J10 -> 90.849907 | H11: =UK!I10 -> 122.01024 | I11: =Iran!I10 -> 391.85347
A12: 2009 | B12: =USA!I11 -> 121.77248 | C12: =Germany!I11 -> 111.71435 | D12: =China!J11 -> 141.73654 | E12: =Italy!I11 -> 125.61562 | F12: =France!I11 -> 117.34392 | G12: =Japan!J11 -> 90.437224 | H12: =UK!I11 -> 124.45953 | I12: =Iran!I11 -> 402.49391
A13: 2010 | B13: =USA!I12 -> 123.25236 | C13: =Germany!I12 -> 112.48818 | D13: =China!J12 -> 151.55158 | E13: =Italy!I12 -> 126.36827 | F13: =France!I12 -> 118.619 | G13: =Japan!J12 -> 88.726783 | H13: =UK!I12 -> 126.11282 | I13: =Iran!I12 -> 460.28919
A14: 2011 | B14: =USA!I13 -> 125.7952 | C14: =Germany!I13 -> 113.87306 | D14: =China!J13 -> 163.64222 | E14: =Italy!I13 -> 128.55102 | F14: =France!I13 -> 119.6342 | G14: =Japan!J13 -> 87.340848 | H14: =UK!I13 -> 129.23532 | I14: =Iran!I13 -> 637.807
... A27: 2024 | B27: =USA!I26 -> 172.47539 | C27: =Germany!I26 -> 159.71769 | D27: =China!J26 -> 202.82385 | E27: =Italy!I26 -> 161.46571 | F27: =France!I26 -> 147.60209 | G27: =Japan!J26 -> 99.926041 | H27: =UK!I26 -> 182.51297 | I27: =Iran!I26 -> 15542.588
A30: Q2 - Real GDP per Capita Index (First Year = 100)
A31: Year | B31: USA | C31: GERMANY | D31: CHINA | E31: ITALY | F31: FRANCE | G31: JAPAN | H31: UK | I31: IRAN
A32: 2000 | B32: =USA!K2 -> 100 | C32: =Germany!K2 -> 100 | D32: =China!L2 -> 100 | E32: =Italy!K2 -> 100 | F32: =France!K2 -> 100 | G32: =Japan!L2 -> 100 | H32: =UK!K2 -> 100 | I32: =Iran!K2 -> 100
A33: 2001 | B33: =USA!K3 -> 99.95492 | C33: =Germany!K3 -> 101.59133 | D33: =China!L3 -> 107.51618 | E33: =Italy!K3 -> 101.79679 | F33: =France!K3 -> 101.09739 | G33: =Japan!L3 -> 100.0296 | H33: =UK!K3 -> 101.9976 | I33: =Iran!K3 -> 100.69562
A34: 2002 | B34: =USA!K4 -> 100.69085 | C34: =Germany!K4 -> 101.23062 | D34: =China!L4 -> 116.62367 | E34: =Italy!K4 -> 101.84673 | F34: =France!K4 -> 101.49566 | G34: =Japan!L4 -> 99.849487 | H34: =UK!K4 -> 103.30252 | I34: =Iran!K4 -> 107.19063
A35: 2003 | B35: =USA!K5 -> 102.55451 | C35: =Germany!K5 -> 100.61393 | D35: =China!L5 -> 127.60537 | E35: =Italy!K5 -> 101.44555 | F35: =France!K5 -> 101.77839 | G35: =Japan!L5 -> 101.04763 | H35: =UK!K5 -> 106.13198 | I35: =Iran!K5 -> 114.69629
A36: 2004 | B36: =USA!K6 -> 105.54328 | C36: =Germany!K6 -> 101.32832 | D36: =China!L6 -> 139.66155 | E36: =Italy!K6 -> 101.95582 | F36: =France!K6 -> 103.58028 | G36: =Japan!L6 -> 103.1371 | H36: =UK!K6 -> 107.98451 | I36: =Iran!K6 -> 117.86693
A37: 2005 | B37: =USA!K7 -> 108.21221 | C37: =Germany!K7 -> 102.459 | D37: =China!L7 -> 154.80947 | E37: =Italy!K7 -> 102.52141 | F37: =France!K7 -> 104.84698 | G37: =Japan!L7 -> 105.03017 | H37: =UK!K7 -> 110.23847 | I37: =Iran!K7 -> 120.97664
A38: 2006 | B38: =USA!K8 -> 110.1739 | C38: =Germany!K8 -> 106.72771 | D38: =China!L8 -> 173.49879 | E38: =Italy!K8 -> 104.04827 | F38: =France!K8 -> 107.1768 | G38: =Japan!L8 -> 106.5593 | H38: =UK!K8 -> 111.82748 | I38: =Iran!K8 -> 125.87233
A39: 2007 | B39: =USA!K9 -> 111.30958 | C39: =Germany!K9 -> 110.07941 | D39: =China!L9 -> 197.10351 | E39: =Italy!K9 -> 104.74334 | F39: =France!K9 -> 109.15653 | G39: =Japan!L9 -> 108.269 | H39: =UK!K9 -> 114.21224 | I39: =Iran!K9 -> 135.67192
A40: 2008 | B40: =USA!K10 -> 110.39426 | C40: =Germany!K10 -> 110.96025 | D40: =China!L10 -> 215.11749 | E40: =Italy!K10 -> 102.83749 | F40: =France!K10 -> 108.83217 | G40: =Japan!L10 -> 106.96217 | H40: =UK!K10 -> 113.26089 | I40: =Iran!K10 -> 135.2198
A41: 2009 | B41: =USA!K11 -> 106.60586 | C41: =Germany!K11 -> 105.12889 | D41: =China!L11 -> 234.17091 | E41: =Italy!K11 -> 96.796985 | F41: =France!K11 -> 105.32446 | G41: =Japan!L11 -> 100.6256 | H41: =UK!K11 -> 107.25084 | I41: =Iran!K11 -> 136.59156
A42: 2010 | B42: =USA!K12 -> 108.56076 | C42: =Germany!K12 -> 109.50143 | D42: =China!L12 -> 257.74521 | E42: =Italy!K12 -> 97.796229 | F42: =France!K12 -> 106.73105 | G42: =Japan!L12 -> 104.76448 | H42: =UK!K12 -> 108.81892 | I42: =Iran!K12 -> 143.68928
A43: 2011 | B43: =USA!K13 -> 109.39198 | C43: =Germany!K13 -> 115.8372 | D43: =China!L13 -> 280.69294 | E43: =Italy!K13 -> 98.293457 | F43: =France!K13 -> 108.85374 | G43: =Japan!L13 -> 104.76398 | H43: =UK!K13 -> 108.89112 | I43: =Iran!K13 -> 147.10874
... A56: 2024 | B56: =USA!K26 -> 137.59676 | C56: =Germany!K26 -> 127.02725 | D56: =China!L26 -> 587.92763 | E56: =Italy!K26 -> 105.61652 | F56: =France!K26 -> 119.83488 | G56: =Japan!L26 -> 119.50752 | H56: =UK!K26 -> 121.84864 | I56: =Iran!K26 -> 164.71213
A59: Q3 - Real GDP Growth Rate (%)
A60: Year | B60: USA | C60: GERMANY | D60: CHINA | E60: ITALY | F60: FRANCE | G60: JAPAN | H60: UK | I60: IRAN
A61: 2000 | B61: =USA!L2 -> 0 | C61: =Germany!L2 -> 0 | D61: =China!M2 -> 0 | E61: =Italy!L2 -> 0 | F61: =France!L2 -> 0 | G61: =Japan!M2 -> 0 | H61: =UK!L2 -> 0 | I61: =Iran!L2 -> 0
A62: 2001 | B62: =USA!L3 -> 0.95553834 | C62: =Germany!L3 -> 1.7623755 | D62: =China!M3 -> 8.3 | E62: =Italy!L3 -> 1.8591362 | F62: =France!L3 -> 1.8370758 | G62: =Japan!M3 -> 0.27091038 | H62: =UK!L3 -> 2.3910223 | I62: =Iran!L3 -> 2.3921727
A63: 2002 | B63: =USA!L4 -> 1.7004473 | C63: =Germany!L4 -> -0.18738918 | D63: =China!M4 -> 9.2 | E63: =Italy!L4 -> 0.24720387 | F63: =France!L4 -> 1.1265049 | G63: =Japan!M4 -> 0.052322798 | H63: =UK!L4 -> 1.7090274 | I63: =Iran!L4 -> 8.0788293
A64: 2003 | B64: =USA!L5 -> 2.7956129 | C64: =Germany!L5 -> -0.55414887 | D64: =China!M5 -> 10.1 | E64: =Italy!L5 -> 0.14584235 | F64: =France!L5 -> 0.9886717 | G64: =Japan!M5 -> 1.4167345 | H64: =UK!L5 -> 3.2185161 | I64: =Iran!L5 -> 8.6392984
A65: 2004 | B65: =USA!L6 -> 3.8477647 | C65: =Germany!L6 -> 0.68817241 | D65: =China!M6 -> 10.1 | E65: =Italy!L6 -> 1.2541511 | F65: =France!L6 -> 2.51874 | G65: =Japan!M6 -> 2.1021676 | H65: =UK!L6 -> 2.3260186 | I65: =Iran!L6 -> 4.336666
A66: 2005 | B66: =USA!L7 -> 3.4835564 | C66: =Germany!L7 -> 1.0584545 | D66: =China!M7 -> 11.5 | E66: =Italy!L7 -> 1.1433382 | F66: =France!L7 -> 1.9868634 | G66: =Japan!M7 -> 1.8450502 | H66: =UK!L7 -> 2.7906547 | I66: =Iran!L7 -> 4.2086904
A67: 2006 | B67: =USA!L8 -> 2.7845332 | C67: =Germany!L8 -> 4.0488389 | D67: =China!M8 -> 12.7 | E67: =Italy!L8 -> 1.8961601 | F67: =France!L8 -> 2.9364104 | G67: =Japan!M8 -> 1.520211 | H67: =UK!L8 -> 2.1898213 | I67: =Iran!L8 -> 5.7042519
A68: 2007 | B68: =USA!L9 -> 2.0038644 | C68: =Germany!L9 -> 3.0025887 | D68: =China!M9 -> 14.2 | E68: =Italy!L9 -> 1.2823563 | F68: =France!L9 -> 2.4787572 | G68: =Japan!M9 -> 1.721278 | H68: =UK!L9 -> 2.9309113 | I68: =Iran!L9 -> 9.1161674
A69: 2008 | B69: =USA!L10 -> 0.11358128 | C69: =Germany!L10 -> 0.60870278 | D69: =China!M10 -> 9.7 | E69: =Italy!L10 -> -1.059357 | F69: =France!L10 -> 0.26076734 | G69: =Japan!M10 -> -1.1591693 | H69: =UK!L10 -> -0.049411655 | I69: =Iran!L10 -> 0.92369579
A70: 2009 | B70: =USA!L11 -> -2.5764943 | C70: =Germany!L11 -> -5.4951172 | D70: =China!M11 -> 9.4 | E70: =Italy!L11 -> -5.326554 | F70: =France!L11 -> -2.7249667 | G70: =Japan!M11 -> -5.9358687 | H70: =UK!L11 -> -4.5874082 | I70: =Iran!L11 -> 2.3147106
A71: 2010 | B71: =USA!L12 -> 2.6951924 | C71: =Germany!L12 -> 3.9997647 | D71: =China!M12 -> 10.6 | E71: =Italy!L12 -> 1.4800897 | F71: =France!L12 -> 1.8362783 | G71: =Japan!M12 -> 4.1318496 | H71: =UK!L12 -> 2.2605446 | I71: =Iran!L12 -> 6.5773744
A72: 2011 | B72: =USA!L13 -> 1.5644068 | C72: =Germany!L13 -> 3.8431119 | D72: =China!M13 -> 9.5 | E72: =Italy!L13 -> 0.85696271 | F72: =France!L13 -> 2.4822774 | G72: =Japan!M13 -> -0.18553755 | H72: =UK!L13 -> 0.85143774 | I72: =Iran!L13 -> 3.7496905
... A85: 2024 | B85: =USA!L26 -> 2.7931872 | C85: =Germany!L26 -> 0.040531606 | D85: =China!M26 -> 5 | E85: =Italy!L26 -> 0.58635074 | F85: =France!L26 -> 1.4263884 | G85: =Japan!M26 -> -0.16090508 | H85: =UK!L26 -> 1.0424161 | I85: =Iran!L26 -> 3.6631206
A88: Q4 - Average Annual Real GDP Growth by Sub-Period (%)
A89: Country | B89: 2000-2007 | C89: 2008-2009 | D89: 2010-2019 | E89: 2020-2024
A90: USA | B90: =AVERAGE(USA!L2:L9) -> 2.5101882 | C90: =AVERAGE(USA!L10:L11) -> -1.2314565 | D90: =AVERAGE(USA!L12:L21) -> 2.3963316 | E90: =AVERAGE(USA!L22:L26) -> 2.4644812
A91: GERMANY | B91: =AVERAGE(Germany!L2:L9) -> 1.4026989 | C91: =AVERAGE(Germany!L10:L11) -> -2.4432072 | D91: =AVERAGE(Germany!L12:L21) -> 2.0666392 | E91: =AVERAGE(Germany!L22:L26) -> 0.13626253
A92: CHINA | B92: =AVERAGE(China!M2:M9) -> 10.871429 | C92: =AVERAGE(China!M10:M11) -> 9.55 | D92: =AVERAGE(China!M12:M21) -> 7.69 | E92: =AVERAGE(China!M22:M26) -> 4.88
A93: ITALY | B93: =AVERAGE(Italy!L2:L9) -> 1.1183126 | C93: =AVERAGE(Italy!L10:L11) -> -3.1929555 | D93: =AVERAGE(Italy!L12:L21) -> 0.23025479 | E93: =AVERAGE(Italy!L22:L26) -> 1.286268
A94: FRANCE | B94: =AVERAGE(France!L2:L9) -> 1.9818605 | C94: =AVERAGE(France!L10:L11) -> -1.2320997 | D94: =AVERAGE(France!L12:L21) -> 1.4165689 | E94: =AVERAGE(France!L22:L26) -> 1.0455992
A95: JAPAN | B95: =AVERAGE(Japan!M2:M9) -> 1.2755249 | C95: =AVERAGE(Japan!M10:M11) -> -3.547519 | D95: =AVERAGE(Japan!M12:M21) -> 1.3130647 | E95: =AVERAGE(Japan!M22:M26) -> 0.23289156
A96: UK | B96: =AVERAGE(UK!L2:L9) -> 2.507996 | C96: =AVERAGE(UK!L10:L11) -> -2.3184099 | D96: =AVERAGE(UK!L12:L21) -> 1.9696664 | E96: =AVERAGE(UK!L22:L26) -> 0.99179704
A97: IRAN | B97: =AVERAGE(Iran!L2:L9) -> 6.0680109 | C97: =AVERAGE(Iran!L10:L11) -> 1.6192032 | D97: =AVERAGE(Iran!L12:L21) -> 1.435035 | E97: =AVERAGE(Iran!L22:L26) -> 4.3841976
A100: Q5 - Output Gap (%)
A101: Year | B101: USA | C101: GERMANY | D101: CHINA | E101: ITALY | F101: FRANCE | G101: JAPAN | H101: UK | I101: IRAN
A102: 2000 | B102: =USA!N2 -> 2.7817049 | C102: =Germany!N2 -> 2.0895782 | D102: =China!O2 -> 95.974353 | E102: =Italy!N2 -> -2.2336395 | F102: =France!N2 -> -1.6059782 | G102: =Japan!O2 -> -0.38620322 | H102: =UK!N2 -> -2.0493186 | I102: =Iran!N2 -> -8.5157233
A103: 2001 | B103: =USA!N3 -> 1.0956702 | C103: =Germany!N3 -> 2.4222733 | D103: =China!O3 -> 44.086052 | E103: =Italy!N3 -> -0.46586673 | F103: =France!N3 -> -1.0572372 | G103: =Japan!O3 -> -0.82505445 | H103: =UK!N3 -> -1.3185308 | I103: =Iran!N3 -> -9.9209222
A104: 2002 | B104: =USA!N4 -> 0.24414229 | C104: =Germany!N4 -> 0.81117041 | D104: =China!O4 -> 19.176729 | E104: =Italy!N4 -> -0.26958847 | F104: =France!N4 -> -1.180716 | G104: =Japan!O4 -> -1.4703612 | H104: =UK!N4 -> -1.2147189 | I104: =Iran!N4 -> -6.2405738
A105: 2003 | B105: =USA!N5 -> 0.53302239 | C105: =Germany!N5 -> -1.1201363 | D105: =China!O5 -> 5.5991902 | E105: =Italy!N5 -> -0.17393616 | F105: =France!N5 -> -1.4234683 | G105: =Japan!O5 -> -0.77166621 | H105: =UK!N5 -> 0.38180151 | I105: =Iran!N5 -> -1.7696911
A106: 2004 | B106: =USA!N6 -> 1.9153324 | C106: =Germany!N6 -> -1.7844449 | D106: =China!O6 -> -2.7245669 | E106: =Italy!N6 -> 1.0276623 | F106: =France!N6 -> -0.16085625 | G106: =Japan!O6 -> 0.61227971 | H106: =UK!N6 -> 1.1465029 | I106: =Iran!N6 -> -1.0358789
A107: 2005 | B107: =USA!N7 -> 3.0061473 | C107: =Germany!N7 -> -2.0712366 | D107: =China!O7 -> -6.8015129 | E107: =Italy!N7 -> 2.1317146 | F107: =France!N7 -> 0.60469914 | G107: =Japan!O7 -> 1.7615957 | H107: =UK!N7 -> 2.3995146 | I107: =Iran!N7 -> -0.30086785
A108: 2006 | B108: =USA!N8 -> 3.4680991 | C108: =Germany!N8 -> 0.55370088 | D108: =China!O8 -> -7.8920303 | E108: =Italy!N8 -> 4.0164858 | F108: =France!N8 -> 2.3379365 | G108: =Japan!O8 -> 2.6025656 | H108: =UK!N8 -> 3.0897716 | I108: =Iran!N8 -> 1.9939001
A109: 2007 | B109: =USA!N9 -> 3.1960436 | C109: =Germany!N9 -> 2.2284724 | D109: =China!O9 -> -6.3395803 | E109: =Italy!N9 -> 5.297926 | F109: =France!N9 -> 3.6526108 | G109: =Japan!O9 -> 3.6602169 | H109: =UK!N9 -> 4.5603415 | I109: =Iran!N9 -> 7.8211346
A110: 2008 | B110: =USA!N10 -> 1.0672678 | C110: =Germany!N10 -> 1.5327796 | D110: =China!O10 -> -7.4018296 | E110: =Italy!N10 -> 4.1306303 | F110: =France!N10 -> 2.7259061 | G110: =Japan!O10 -> 1.7678488 | H110: =UK!N10 -> 3.003203 | I110: =Iran!N10 -> 5.526179
A111: 2009 | B111: =USA!N11 -> -3.6373479 | C111: =Germany!N11 -> -5.2638689 | D111: =China!O11 -> -7.825814 | E111: =Italy!N11 -> -1.4650843 | F111: =France!N11 -> -1.214284 | G111: =Japan!O11 -> -4.9157663 | H111: =UK!N11 -> -3.1213588 | I111: =Iran!N11 -> 4.7994137
A112: 2010 | B112: =USA!N12 -> -3.1017753 | C112: =Germany!N12 -> -2.7055895 | D112: =China!O12 -> -6.4609861 | E112: =Italy!N12 -> -0.056361011 | F112: =France!N12 -> -0.53289661 | G112: =Japan!O12 -> -1.6456758 | H112: =UK!N12 -> -2.3184646 | I112: =Iran!N12 -> 8.5072661
A113: 2011 | B113: =USA!N13 -> -3.5942712 | C113: =Germany!N13 -> -0.21316001 | D113: =China!O13 -> -5.3767452 | E113: =Italy!N13 -> 0.75006082 | F113: =France!N13 -> 0.80128988 | G113: =Japan!O13 -> -2.4768963 | H113: =UK!N13 -> -2.8470361 | I113: =Iran!N13 -> 9.4545745
... A126: 2024 | B126: =USA!N26 -> 4.3544377 | C126: =Germany!N26 -> -1.901148 | D126: =China!O26 -> 4.2840559 | E126: =Italy!N26 -> 5.6365722 | F126: =France!N26 -> 1.6954491 | G126: =Japan!O26 -> -0.6497031 | H126: =UK!N26 -> 0.9337183 | I126: =Iran!N26 -> 3.0417167
A129: Q6 - CPI Inflation Rate (%)
A130: Year | B130: USA | C130: GERMANY | D130: CHINA | E130: ITALY | F130: FRANCE | G130: JAPAN | H130: UK | I130: IRAN
A131: 2000 | B131: =USA!O2 -> 0 | C131: =Germany!O2 -> 0 | D131: =China!P2 -> 0 | E131: =Italy!O2 -> 0 | F131: =France!O2 -> 0 | G131: =Japan!P2 -> 0 | H131: =UK!O2 -> 0 | I131: =Iran!O2 -> 0
A132: 2001 | B132: =USA!O3 -> 2.8166233 | C132: =Germany!O3 -> 1.9838525 | D132: =China!P3 -> 0.71913244 | E132: =Italy!O3 -> 2.7851654 | F132: =France!O3 -> 1.6347808 | G132: =Japan!P3 -> -0.7400555 | H132: =UK!O3 -> 1.5323496 | I132: =Iran!O3 -> 11.541502
A133: 2002 | B133: =USA!O4 -> 1.5956666 | C133: =Germany!O4 -> 1.420808 | D133: =China!P4 -> -0.7319755 | E133: =Italy!O4 -> 2.4653232 | F133: =France!O4 -> 1.9234123 | G133: =Japan!P4 -> -0.92349403 | H133: =UK!O4 -> 1.5204025 | I133: =Iran!O4 -> 13.217576
A134: 2003 | B134: =USA!O5 -> 2.2978089 | C134: =Germany!O5 -> 1.0342247 | D134: =China!P5 -> 1.127602 | E134: =Italy!O5 -> 2.6725555 | F134: =France!O5 -> 2.0984722 | G134: =Japan!P5 -> -0.25654182 | H134: =UK!O5 -> 1.3765004 | I134: =Iran!O5 -> 13.896714
A135: 2004 | B135: =USA!O6 -> 2.6673913 | C135: =Germany!O6 -> 1.6657331 | D135: =China!P6 -> 3.8246376 | E135: =Italy!O6 -> 2.2067366 | F135: =France!O6 -> 2.1420896 | G135: =Japan!P6 -> -0.0085733882 | H135: =UK!O6 -> 1.3903976 | I135: =Iran!O6 -> 14.619401
A136: 2005 | B136: =USA!O7 -> 3.3661888 | C136: =Germany!O7 -> 1.5469109 | D136: =China!P7 -> 1.7764162 | E136: =Italy!O7 -> 1.985293 | F136: =France!O7 -> 1.7458694 | G136: =Japan!P7 -> -0.28294607 | H136: =UK!O7 -> 2.0891365 | I136: =Iran!O7 -> 12.107408
A137: 2006 | B137: =USA!O8 -> 3.2217425 | C137: =Germany!O8 -> 1.577433 | D137: =China!P8 -> 1.6494331 | E137: =Italy!O8 -> 2.0908439 | F137: =France!O8 -> 1.6751245 | G137: =Japan!P8 -> 0.24935512 | H137: =UK!O8 -> 2.4556617 | I137: =Iran!O8 -> 13.686912
A138: 2007 | B138: =USA!O9 -> 2.8706377 | C138: =Germany!O9 -> 2.2983353 | D138: =China!P9 -> 4.8167653 | E138: =Italy!O9 -> 1.8297411 | F138: =France!O9 -> 1.4879981 | G138: =Japan!P9 -> 0.060039454 | H138: =UK!O9 -> 2.3865615 | I138: =Iran!O9 -> 17.231001
A139: 2008 | B139: =USA!O10 -> 3.8149163 | C139: =Germany!O10 -> 2.6283882 | D139: =China!P10 -> 5.9252553 | E139: =Italy!O10 -> 3.3478326 | F139: =France!O10 -> 2.8128619 | G139: =Japan!P10 -> 1.3800789 | H139: =UK!O10 -> 3.5214086 | I139: =Iran!O10 -> 25.545571
A140: 2009 | B140: =USA!O11 -> -0.32008697 | C140: =Germany!O11 -> 0.31273714 | D140: =China!P11 -> -0.72817133 | E140: =Italy!O11 -> 0.77476813 | F140: =France!O11 -> 0.087620478 | G140: =Japan!P11 -> -1.3528367 | H140: =UK!O11 -> 1.9617317 | I140: =Iran!O11 -> 9.4708589
A141: 2010 | B141: =USA!O12 -> 1.636334 | C141: =Germany!O12 -> 1.1038067 | D141: =China!P12 -> 3.175328 | E141: =Italy!O12 -> 1.525516 | F141: =France!O12 -> 1.5311227 | G141: =Japan!P12 -> -0.72824321 | H141: =UK!O12 -> 2.4926547 | I141: =Iran!O12 -> 13.92878
A142: 2011 | B142: =USA!O13 -> 3.1397311 | C142: =Germany!O13 -> 2.0751744 | D142: =China!P13 -> 5.5538971 | E142: =Italy!O13 -> 2.7806327 | F142: =France!O13 -> 2.111598 | G142: =Japan!P13 -> -0.27245562 | H142: =UK!O13 -> 3.8561124 | I142: =Iran!O13 -> 26.35786
... A155: 2024 | B155: =USA!O26 -> 2.952055 | C155: =Germany!O26 -> 2.2564933 | D155: =China!P26 -> 0.21812572 | E155: =Italy!O26 -> 0.98237302 | F155: =France!O26 -> 1.9990494 | G155: =Japan!P26 -> 2.7385368 | H155: =UK!O26 -> 3.2715729 | I155: =Iran!O26 -> 32.788782
A166: Q7 - Average Absolute Gap Between CPI Inflation and GDP Deflator Inflation (pp)
A167: Country | B167: Avg |CPI Inflation - Deflator Inflation| (pp)
A168: USA | B168: =SUMPRODUCT(ABS(USA!O3:O26-USA!P3:P26))/COUNT(USA!O3:O26) -> 0.4224094
A169: GERMANY | B169: =SUMPRODUCT(ABS(Germany!O3:O26-Germany!P3:P26))/COUNT(Germany!O3:O26) -> 0.76386576
A170: CHINA | B170: =SUMPRODUCT(ABS(China!P3:P26-China!Q3:Q26))/COUNT(China!P3:P26) -> 1.6503994
A171: ITALY | B171: =SUMPRODUCT(ABS(Italy!O3:O26-Italy!P3:P26))/COUNT(Italy!O3:O26) -> 0.86245048
A172: FRANCE | B172: =SUMPRODUCT(ABS(France!O3:O26-France!P3:P26))/COUNT(France!O3:O26) -> 0.58509834
A173: JAPAN | B173: =SUMPRODUCT(ABS(Japan!P3:P26-Japan!Q3:Q26))/COUNT(Japan!P3:P26) -> 0.9790884
A174: UK | B174: =SUMPRODUCT(ABS(UK!O3:O26-UK!P3:P26))/COUNT(UK!O3:O26) -> 0.8794654
A175: IRAN | B175: =SUMPRODUCT(ABS(Iran!O3:O26-Iran!P3:P26))/COUNT(Iran!O3:O26) -> 6.4775893
A194: Q8 - Unemployment Rate (%)
A195: Year | B195: USA | C195: GERMANY | D195: CHINA | E195: ITALY | F195: FRANCE | G195: JAPAN | H195: UK | I195: IRAN
A196: 2000 | B196: =USA!B2 -> 4 | C196: =Germany!B2 -> 8 | D196: =China!B2 -> 6.84 | E196: =Italy!B2 -> 10.1 | F196: =France!B2 -> 9.2 | G196: =Japan!B2 -> 4.7 | H196: =UK!B2 -> 5.5 | I196: =Iran!B2 -> 0
A197: 2001 | B197: =USA!B3 -> 4.7 | C197: =Germany!B3 -> 7.8 | D197: =China!B3 -> 7.994 | E197: =Italy!B3 -> 9.1 | F197: =France!B3 -> 8.5 | G197: =Japan!B3 -> 5 | H197: =UK!B3 -> 5.1 | I197: =Iran!B3 -> 0
A198: 2002 | B198: =USA!B4 -> 5.8 | C198: =Germany!B4 -> 8.6 | D198: =China!B4 -> 8.919 | E198: =Italy!B4 -> 8.6 | F198: =France!B4 -> 8.3 | G198: =Japan!B4 -> 5.4 | H198: =UK!B4 -> 5.2 | I198: =Iran!B4 -> 0
...
